{
"meta":{"test_sets":[],"test_metrics":[],"learn_metrics":[{"best_value":"Min","name":"RMSE"}],"launch_mode":"Train","parameters":"","iteration_count":1000,"learn_sets":["learn"],"name":"experiment"},
"iterations":[
{"learn":[14.59871775],"iteration":0,"passed_time":0.05762558418,"remaining_time":57.56795859},
{"learn":[14.22518863],"iteration":1,"passed_time":0.05797412324,"remaining_time":28.9290875},
{"learn":[13.8866124],"iteration":2,"passed_time":0.05834419867,"remaining_time":19.38972202},
{"learn":[13.52356875],"iteration":3,"passed_time":0.05862717057,"remaining_time":14.59816547},
{"learn":[13.18870211],"iteration":4,"passed_time":0.05893242864,"remaining_time":11.7275533},
{"learn":[12.9124226],"iteration":5,"passed_time":0.05926218068,"remaining_time":9.817767932},
{"learn":[12.60003351],"iteration":6,"passed_time":0.05958801701,"remaining_time":8.452985841},
{"learn":[12.32990573],"iteration":7,"passed_time":0.05986682327,"remaining_time":7.423486085},
{"learn":[12.0660619],"iteration":8,"passed_time":0.06013938107,"remaining_time":6.622014071},
{"learn":[11.77309809],"iteration":9,"passed_time":0.06051553833,"remaining_time":5.991038295},
{"learn":[11.49227636],"iteration":10,"passed_time":0.06095876239,"remaining_time":5.480746909},
{"learn":[11.26264833],"iteration":11,"passed_time":0.0611838319,"remaining_time":5.037468826},
{"learn":[11.04260393],"iteration":12,"passed_time":0.06150954326,"remaining_time":4.669993784},
{"learn":[10.79916926],"iteration":13,"passed_time":0.06177931008,"remaining_time":4.351028553},
{"learn":[10.5541002],"iteration":14,"passed_time":0.06214122085,"remaining_time":4.080606836},
{"learn":[10.31918115],"iteration":15,"passed_time":0.06245326892,"remaining_time":3.840876038},
{"learn":[10.10004441],"iteration":16,"passed_time":0.06272157777,"remaining_time":3.626782997},
{"learn":[9.894556723],"iteration":17,"passed_time":0.06303395908,"remaining_time":3.438852657},
{"learn":[9.690174082],"iteration":18,"passed_time":0.06336591891,"remaining_time":3.271682445},
{"learn":[9.506034866],"iteration":19,"passed_time":0.06369762879,"remaining_time":3.121183811},
{"learn":[9.338524633],"iteration":20,"passed_time":0.0640213823,"remaining_time":2.98461587},
{"learn":[9.170203312],"iteration":21,"passed_time":0.0642408282,"remaining_time":2.855796817},
{"learn":[9.010299969],"iteration":22,"passed_time":0.06452517476,"remaining_time":2.740917206},
{"learn":[8.843866678],"iteration":23,"passed_time":0.06481589475,"remaining_time":2.635846386},
{"learn":[8.690548059],"iteration":24,"passed_time":0.06515756051,"remaining_time":2.54114486},
{"learn":[8.555307687],"iteration":25,"passed_time":0.06553238477,"remaining_time":2.454943952},
{"learn":[8.413851302],"iteration":26,"passed_time":0.06580727533,"remaining_time":2.371499218},
{"learn":[8.29256019],"iteration":27,"passed_time":0.06606741952,"remaining_time":2.293483278},
{"learn":[8.162193833],"iteration":28,"passed_time":0.0663079019,"remaining_time":2.220171474},
{"learn":[8.040736294],"iteration":29,"passed_time":0.06655492433,"remaining_time":2.151942553},
{"learn":[7.921220278],"iteration":30,"passed_time":0.06689538206,"remaining_time":2.091020168},
{"learn":[7.809589039],"iteration":31,"passed_time":0.0671913091,"remaining_time":2.0325371},
{"learn":[7.699675801],"iteration":32,"passed_time":0.06758258763,"remaining_time":1.980374613},
{"learn":[7.60645267],"iteration":33,"passed_time":0.06791758837,"remaining_time":1.92965854},
{"learn":[7.498880302],"iteration":34,"passed_time":0.06817390017,"remaining_time":1.879651819},
{"learn":[7.401158744],"iteration":35,"passed_time":0.06845524747,"remaining_time":1.833079405},
{"learn":[7.306431077],"iteration":36,"passed_time":0.06873551171,"remaining_time":1.788981021},
{"learn":[7.223863468],"iteration":37,"passed_time":0.06900057136,"remaining_time":1.746803938},
{"learn":[7.143477682],"iteration":38,"passed_time":0.06928246019,"remaining_time":1.707190878},
{"learn":[7.062817131],"iteration":39,"passed_time":0.06957855386,"remaining_time":1.669885293},
{"learn":[6.990793435],"iteration":40,"passed_time":0.0698439051,"remaining_time":1.633665975},
{"learn":[6.931862224],"iteration":41,"passed_time":0.07017953069,"remaining_time":1.600761676},
{"learn":[6.858296558],"iteration":42,"passed_time":0.0705062418,"remaining_time":1.5691738},
{"learn":[6.786268161],"iteration":43,"passed_time":0.07087111018,"remaining_time":1.539835939},
{"learn":[6.717118549],"iteration":44,"passed_time":0.07115362386,"remaining_time":1.510038017},
{"learn":[6.652948106],"iteration":45,"passed_time":0.07144784299,"remaining_time":1.481766135},
{"learn":[6.589686076],"iteration":46,"passed_time":0.0716908664,"remaining_time":1.453646717},
{"learn":[6.531283097],"iteration":47,"passed_time":0.07194442889,"remaining_time":1.42689784},
{"learn":[6.471368031],"iteration":48,"passed_time":0.07226085088,"remaining_time":1.402450391},
{"learn":[6.416481395],"iteration":49,"passed_time":0.07262405299,"remaining_time":1.379857007},
{"learn":[6.369870822],"iteration":50,"passed_time":0.07288161449,"remaining_time":1.35616965},
{"learn":[6.325678067],"iteration":51,"passed_time":0.07315812965,"remaining_time":1.333728979},
{"learn":[6.275766122],"iteration":52,"passed_time":0.07341414986,"remaining_time":1.311758489},
{"learn":[6.224773967],"iteration":53,"passed_time":0.07369070668,"remaining_time":1.29095201},
{"learn":[6.182249254],"iteration":54,"passed_time":0.07397946882,"remaining_time":1.271101782},
{"learn":[6.139904173],"iteration":55,"passed_time":0.07427681218,"remaining_time":1.252094834},
{"learn":[6.100525536],"iteration":56,"passed_time":0.07458302835,"remaining_time":1.233891153},
{"learn":[6.062568564],"iteration":57,"passed_time":0.07487074908,"remaining_time":1.216004235},
{"learn":[6.030559288],"iteration":58,"passed_time":0.07514588957,"remaining_time":1.198513256},
{"learn":[5.997931376],"iteration":59,"passed_time":0.07548855509,"remaining_time":1.18265403},
{"learn":[5.964103835],"iteration":60,"passed_time":0.07582105645,"remaining_time":1.167147082},
{"learn":[5.933729724],"iteration":61,"passed_time":0.07610865221,"remaining_time":1.151450254},
{"learn":[5.901932711],"iteration":62,"passed_time":0.07635325857,"remaining_time":1.135603227},
{"learn":[5.873727795],"iteration":63,"passed_time":0.07664997708,"remaining_time":1.121005915},
{"learn":[5.846485734],"iteration":64,"passed_time":0.07693469855,"remaining_time":1.106676048},
{"learn":[5.820630862],"iteration":65,"passed_time":0.07720629825,"remaining_time":1.092586099},
{"learn":[5.793646238],"iteration":66,"passed_time":0.07761019867,"remaining_time":1.080750975},
{"learn":[5.765388646],"iteration":67,"passed_time":0.07799635346,"remaining_time":1.069008845},
{"learn":[5.747073912],"iteration":68,"passed_time":0.07831664949,"remaining_time":1.056707256},
{"learn":[5.722315217],"iteration":69,"passed_time":0.07869588933,"remaining_time":1.045531101},
{"learn":[5.699970599],"iteration":70,"passed_time":0.07901764333,"remaining_time":1.033906911},
{"learn":[5.682732647],"iteration":71,"passed_time":0.07926708183,"remaining_time":1.02166461},
{"learn":[5.663525791],"iteration":72,"passed_time":0.07956263397,"remaining_time":1.010336461},
{"learn":[5.642381613],"iteration":73,"passed_time":0.07989430219,"remaining_time":0.9997584302},
{"learn":[5.621404779],"iteration":74,"passed_time":0.08016690165,"remaining_time":0.9887251204},
{"learn":[5.602460129],"iteration":75,"passed_time":0.08048182401,"remaining_time":0.9784895445},
{"learn":[5.587337574],"iteration":76,"passed_time":0.08080374464,"remaining_time":0.9685955364},
{"learn":[5.572393026],"iteration":77,"passed_time":0.08116044836,"remaining_time":0.9593581204},
{"learn":[5.558425806],"iteration":78,"passed_time":0.08150473848,"remaining_time":0.9502008119},
{"learn":[5.541518902],"iteration":79,"passed_time":0.08175309391,"remaining_time":0.94016058},
{"learn":[5.526157283],"iteration":80,"passed_time":0.08204368893,"remaining_time":0.9308413596},
{"learn":[5.511746977],"iteration":81,"passed_time":0.08233249273,"remaining_time":0.9217222966},
{"learn":[5.504975022],"iteration":82,"passed_time":0.08246612645,"remaining_time":0.9111016621},
{"learn":[5.493980522],"iteration":83,"passed_time":0.08279696155,"remaining_time":0.9028811521},
{"learn":[5.480745463],"iteration":84,"passed_time":0.08310846808,"remaining_time":0.8946382152},
{"learn":[5.464052013],"iteration":85,"passed_time":0.08342613976,"remaining_time":0.8866452528},
{"learn":[5.449143727],"iteration":86,"passed_time":0.08379500715,"remaining_time":0.8793659946},
{"learn":[5.438255432],"iteration":87,"passed_time":0.08407393838,"remaining_time":0.871311725},
{"learn":[5.425927931],"iteration":88,"passed_time":0.08431900296,"remaining_time":0.8630855247},
{"learn":[5.412331217],"iteration":89,"passed_time":0.0845934353,"remaining_time":0.8553336236},
{"learn":[5.400691499],"iteration":90,"passed_time":0.08492552009,"remaining_time":0.8483219534},
{"learn":[5.391618744],"iteration":91,"passed_time":0.08521232438,"remaining_time":0.8410085928},
{"learn":[5.380766572],"iteration":92,"passed_time":0.08548429899,"remaining_time":0.8337017116},
{"learn":[5.372207183],"iteration":93,"passed_time":0.08578664111,"remaining_time":0.8268372005},
{"learn":[5.362918837],"iteration":94,"passed_time":0.08615725807,"remaining_time":0.820761248},
{"learn":[5.348292324],"iteration":95,"passed_time":0.08648392753,"remaining_time":0.8143903176},
{"learn":[5.339772295],"iteration":96,"passed_time":0.08676265048,"remaining_time":0.8076976638},
{"learn":[5.331515983],"iteration":97,"passed_time":0.0870060488,"remaining_time":0.8008107757},
{"learn":[5.323861644],"iteration":98,"passed_time":0.08729368622,"remaining_time":0.7944607201},
{"learn":[5.313277281],"iteration":99,"passed_time":0.08762906187,"remaining_time":0.7886615568},
{"learn":[5.30685627],"iteration":100,"passed_time":0.08790511881,"remaining_time":0.7824425922},
{"learn":[5.29652059],"iteration":101,"passed_time":0.08817559379,"remaining_time":0.776291012},
{"learn":[5.288350766],"iteration":102,"passed_time":0.08848747523,"remaining_time":0.770614226},
{"learn":[5.27993346],"iteration":103,"passed_time":0.088777737,"remaining_time":0.7648543495},
{"learn":[5.271789139],"iteration":104,"passed_time":0.08909178457,"remaining_time":0.7594014018},
{"learn":[5.262684686],"iteration":105,"passed_time":0.08934847128,"remaining_time":0.7535616352},
{"learn":[5.251619772],"iteration":106,"passed_time":0.08964510648,"remaining_time":0.748159627},
{"learn":[5.241012171],"iteration":107,"passed_time":0.08989379517,"remaining_time":0.7424561601},
{"learn":[5.232684032],"iteration":108,"passed_time":0.09014869066,"remaining_time":0.7369035172},
{"learn":[5.224267141],"iteration":109,"passed_time":0.09041350037,"remaining_time":0.7315274121},
{"learn":[5.216324968],"iteration":110,"passed_time":0.09067435272,"remaining_time":0.7262117079},
{"learn":[5.211102527],"iteration":111,"passed_time":0.09091071112,"remaining_time":0.7207920667},
{"learn":[5.206364257],"iteration":112,"passed_time":0.0912310488,"remaining_time":0.7161233654},
{"learn":[5.196937641],"iteration":113,"passed_time":0.0915488038,"remaining_time":0.7115108786},
{"learn":[5.190746047],"iteration":114,"passed_time":0.09184044023,"remaining_time":0.7067720835},
{"learn":[5.181885213],"iteration":115,"passed_time":0.0921160806,"remaining_time":0.7019880625},
{"learn":[5.178293568],"iteration":116,"passed_time":0.09241983904,"remaining_time":0.6974933152},
{"learn":[5.170991438],"iteration":117,"passed_time":0.0927532985,"remaining_time":0.693291604},
{"learn":[5.166257212],"iteration":118,"passed_time":0.09315486616,"remaining_time":0.6896591352},
{"learn":[5.161421246],"iteration":119,"passed_time":0.09344196204,"remaining_time":0.685241055},
{"learn":[5.158223542],"iteration":120,"passed_time":0.09386364974,"remaining_time":0.6818689927},
{"learn":[5.15470988],"iteration":121,"passed_time":0.09413612423,"remaining_time":0.6774714514},
{"learn":[5.146388143],"iteration":122,"passed_time":0.09446700099,"remaining_time":0.6735573973},
{"learn":[5.139529364],"iteration":123,"passed_time":0.09474801504,"remaining_time":0.6693488804},
{"learn":[5.134276023],"iteration":124,"passed_time":0.09500578482,"remaining_time":0.6650404937},
{"learn":[5.128536065],"iteration":125,"passed_time":0.09529238082,"remaining_time":0.6609963559},
{"learn":[5.123300353],"iteration":126,"passed_time":0.09554523515,"remaining_time":0.6567794511},
{"learn":[5.116200518],"iteration":127,"passed_time":0.09582312497,"remaining_time":0.6527950389},
{"learn":[5.108728704],"iteration":128,"passed_time":0.09618624378,"remaining_time":0.6494435529},
{"learn":[5.104075866],"iteration":129,"passed_time":0.09643847326,"remaining_time":0.6453959364},
{"learn":[5.100317606],"iteration":130,"passed_time":0.09672773527,"remaining_time":0.6416519233},
{"learn":[5.095814182],"iteration":131,"passed_time":0.09697854843,"remaining_time":0.6377074246},
{"learn":[5.092146915],"iteration":132,"passed_time":0.0972753086,"remaining_time":0.6341179892},
{"learn":[5.085258329],"iteration":133,"passed_time":0.09753103722,"remaining_time":0.6303125241},
{"learn":[5.079219421],"iteration":134,"passed_time":0.09778147547,"remaining_time":0.6265257503},
{"learn":[5.076476829],"iteration":135,"passed_time":0.09805295021,"remaining_time":0.6229246249},
{"learn":[5.072133867],"iteration":136,"passed_time":0.09831321937,"remaining_time":0.6193015206},
{"learn":[5.067031564],"iteration":137,"passed_time":0.09858702687,"remaining_time":0.6158117185},
{"learn":[5.061358312],"iteration":138,"passed_time":0.09889599236,"remaining_time":0.6125859671},
{"learn":[5.056759124],"iteration":139,"passed_time":0.0991782561,"remaining_time":0.6092378589},
{"learn":[5.050254],"iteration":140,"passed_time":0.09942390387,"remaining_time":0.6057101661},
{"learn":[5.048376474],"iteration":141,"passed_time":0.09968129874,"remaining_time":0.6022996783},
{"learn":[5.042603751],"iteration":142,"passed_time":0.1000218814,"remaining_time":0.5994318349},
{"learn":[5.037477349],"iteration":143,"passed_time":0.1002647382,"remaining_time":0.5960181661},
{"learn":[5.03230489],"iteration":144,"passed_time":0.1005412117,"remaining_time":0.5928464554},
{"learn":[5.025976187],"iteration":145,"passed_time":0.1007811942,"remaining_time":0.589500958},
{"learn":[5.01952451],"iteration":146,"passed_time":0.1010115958,"remaining_time":0.5861421169},
{"learn":[5.017569424],"iteration":147,"passed_time":0.1012482874,"remaining_time":0.5828617626},
{"learn":[5.008962367],"iteration":148,"passed_time":0.1014765228,"remaining_time":0.5795739658},
{"learn":[5.003880266],"iteration":149,"passed_time":0.101720546,"remaining_time":0.5764164272},
{"learn":[4.996387564],"iteration":150,"passed_time":0.1019478649,"remaining_time":0.5732035584},
{"learn":[4.993361683],"iteration":151,"passed_time":0.1021993029,"remaining_time":0.5701645322},
{"learn":[4.99005752],"iteration":152,"passed_time":0.1024266219,"remaining_time":0.5670284231},
{"learn":[4.986908764],"iteration":153,"passed_time":0.1026586897,"remaining_time":0.5639561783},
{"learn":[4.985207175],"iteration":154,"passed_time":0.1028850922,"remaining_time":0.5608896961},
{"learn":[4.979003494],"iteration":155,"passed_time":0.1031404459,"remaining_time":0.5580162586},
{"learn":[4.973142217],"iteration":156,"passed_time":0.1033619746,"remaining_time":0.5549945516},
{"learn":[4.967056696],"iteration":157,"passed_time":0.1035938758,"remaining_time":0.5520635658},
{"learn":[4.961460696],"iteration":158,"passed_time":0.1038219029,"remaining_time":0.5491460398},
{"learn":[4.954240363],"iteration":159,"passed_time":0.104146073,"remaining_time":0.546766883},
{"learn":[4.952320707],"iteration":160,"passed_time":0.1042930367,"remaining_time":0.5434898001},
{"learn":[4.948337777],"iteration":161,"passed_time":0.1053548166,"remaining_time":0.5449835575},
{"learn":[4.943228639],"iteration":162,"passed_time":0.1055801777,"remaining_time":0.5421509739},
{"learn":[4.938545759],"iteration":163,"passed_time":0.1058310325,"remaining_time":0.5394801415},
{"learn":[4.935330572],"iteration":164,"passed_time":0.1061469546,"remaining_time":0.537167922},
{"learn":[4.932051543],"iteration":165,"passed_time":0.1065331928,"remaining_time":0.5352330287},
{"learn":[4.928964153],"iteration":166,"passed_time":0.1068495314,"remaining_time":0.532968022},
{"learn":[4.922860227],"iteration":167,"passed_time":0.1072092761,"remaining_time":0.5309411767},
{"learn":[4.917668772],"iteration":168,"passed_time":0.1075623973,"remaining_time":0.5289014922},
{"learn":[4.910365386],"iteration":169,"passed_time":0.1078245827,"remaining_time":0.5264376685},
{"learn":[4.906457206],"iteration":170,"passed_time":0.1080938913,"remaining_time":0.524034128},
{"learn":[4.901996508],"iteration":171,"passed_time":0.1084057727,"remaining_time":0.5218603478},
{"learn":[4.896816173],"iteration":172,"passed_time":0.1086685829,"remaining_time":0.519473515},
{"learn":[4.891123132],"iteration":173,"passed_time":0.1089024003,"remaining_time":0.5169734635},
{"learn":[4.887630202],"iteration":174,"passed_time":0.1091650439,"remaining_time":0.5146352068},
{"learn":[4.885259712],"iteration":175,"passed_time":0.1093894052,"remaining_time":0.5121413063},
{"learn":[4.880659728],"iteration":176,"passed_time":0.1096944134,"remaining_time":0.510048035},
{"learn":[4.877299723],"iteration":177,"passed_time":0.1099645134,"remaining_time":0.5078136519},
{"learn":[4.874038772],"iteration":178,"passed_time":0.1102342803,"remaining_time":0.5055996877},
{"learn":[4.86943698],"iteration":179,"passed_time":0.1104653066,"remaining_time":0.5032308413},
{"learn":[4.861268711],"iteration":180,"passed_time":0.1107949754,"remaining_time":0.5013319603},
{"learn":[4.858673056],"iteration":181,"passed_time":0.1110298341,"remaining_time":0.4990241995},
{"learn":[4.854036207],"iteration":182,"passed_time":0.1112811888,"remaining_time":0.4968127391},
{"learn":[4.85130244],"iteration":183,"passed_time":0.1116412667,"remaining_time":0.495104748},
{"learn":[4.847510084],"iteration":184,"passed_time":0.1119999283,"remaining_time":0.4934050894},
{"learn":[4.845691673],"iteration":185,"passed_time":0.1122905649,"remaining_time":0.4914221498},
{"learn":[4.842058646],"iteration":186,"passed_time":0.1125803268,"remaining_time":0.4894535065},
{"learn":[4.838623675],"iteration":187,"passed_time":0.1128584249,"remaining_time":0.487452346},
{"learn":[4.834602161],"iteration":188,"passed_time":0.1131123623,"remaining_time":0.4853657453},
{"learn":[4.830858976],"iteration":189,"passed_time":0.1134090392,"remaining_time":0.4834806408},
{"learn":[4.827590511],"iteration":190,"passed_time":0.1136547703,"remaining_time":0.481396383},
{"learn":[4.822246226],"iteration":191,"passed_time":0.1139067082,"remaining_time":0.4793573968},
{"learn":[4.816686395],"iteration":192,"passed_time":0.114164103,"remaining_time":0.4773597469},
{"learn":[4.814797121],"iteration":193,"passed_time":0.1144263717,"remaining_time":0.4754002866},
{"learn":[4.811639392],"iteration":194,"passed_time":0.1146980131,"remaining_time":0.4734969257},
{"learn":[4.804813432],"iteration":195,"passed_time":0.1149453271,"remaining_time":0.4715104234},
{"learn":[4.80251613],"iteration":196,"passed_time":0.1152487523,"remaining_time":0.4697702948},
{"learn":[4.800087884],"iteration":197,"passed_time":0.1155095213,"remaining_time":0.4678718995},
{"learn":[4.794773135],"iteration":198,"passed_time":0.1157637087,"remaining_time":0.4659634705},
{"learn":[4.791664833],"iteration":199,"passed_time":0.1160686335,"remaining_time":0.4642745339},
{"learn":[4.785989873],"iteration":200,"passed_time":0.1163531467,"remaining_time":0.4625182298},
{"learn":[4.782387142],"iteration":201,"passed_time":0.1166000441,"remaining_time":0.4606278971},
{"learn":[4.778623704],"iteration":202,"passed_time":0.1168324452,"remaining_time":0.4586968413},
{"learn":[4.775772178],"iteration":203,"passed_time":0.1171025036,"remaining_time":0.4569293767},
{"learn":[4.77023101],"iteration":204,"passed_time":0.117348068,"remaining_time":0.4550815321},
{"learn":[4.764496689],"iteration":205,"passed_time":0.1176203759,"remaining_time":0.4533523226},
{"learn":[4.763138716],"iteration":206,"passed_time":0.1178880599,"remaining_time":0.4516194758},
{"learn":[4.758053283],"iteration":207,"passed_time":0.118162284,"remaining_time":0.4499256197},
{"learn":[4.755063788],"iteration":208,"passed_time":0.1184639596,"remaining_time":0.4483492441},
{"learn":[4.752465267],"iteration":209,"passed_time":0.1188364511,"remaining_time":0.4470514112},
{"learn":[4.748067377],"iteration":210,"passed_time":0.11919228,"remaining_time":0.4457000423},
{"learn":[4.744163298],"iteration":211,"passed_time":0.1195120762,"remaining_time":0.4442241322},
{"learn":[4.736670896],"iteration":212,"passed_time":0.1197810932,"remaining_time":0.4425714569},
{"learn":[4.73349255],"iteration":213,"passed_time":0.1200404042,"remaining_time":0.4408960642},
{"learn":[4.731864595],"iteration":214,"passed_time":0.1202912174,"remaining_time":0.439202817},
{"learn":[4.728398311],"iteration":215,"passed_time":0.1205663579,"remaining_time":0.437611225},
{"learn":[4.723865975],"iteration":216,"passed_time":0.1208731573,"remaining_time":0.4361460006},
{"learn":[4.723483365],"iteration":217,"passed_time":0.1211184718,"remaining_time":0.4344708483},
{"learn":[4.72095416],"iteration":218,"passed_time":0.1213889884,"remaining_time":0.4328986299},
{"learn":[4.716173382],"iteration":219,"passed_time":0.1216566308,"remaining_time":0.4313280545},
{"learn":[4.710563974],"iteration":220,"passed_time":0.1219067358,"remaining_time":0.4297074532},
{"learn":[4.707160263],"iteration":221,"passed_time":0.1221817096,"remaining_time":0.4281863518},
{"learn":[4.70408351],"iteration":222,"passed_time":0.1224869261,"remaining_time":0.4267818006},
{"learn":[4.702501831],"iteration":223,"passed_time":0.1228754553,"remaining_time":0.4256756843},
{"learn":[4.700269738],"iteration":224,"passed_time":0.1231669251,"remaining_time":0.4242416308},
{"learn":[4.695346302],"iteration":225,"passed_time":0.1234828472,"remaining_time":0.4229014324},
{"learn":[4.689769299],"iteration":226,"passed_time":0.1237476152,"remaining_time":0.4213960642},
{"learn":[4.687919514],"iteration":227,"passed_time":0.1240307954,"remaining_time":0.4199639213},
{"learn":[4.682982074],"iteration":228,"passed_time":0.1243847915,"remaining_time":0.4187802368},
{"learn":[4.679578702],"iteration":229,"passed_time":0.1246940902,"remaining_time":0.4174541281},
{"learn":[4.675751423],"iteration":230,"passed_time":0.1249678144,"remaining_time":0.4160183951},
{"learn":[4.672710726],"iteration":231,"passed_time":0.1252570764,"remaining_time":0.414644115},
{"learn":[4.6690533],"iteration":232,"passed_time":0.125504932,"remaining_time":0.4131428447},
{"learn":[4.667595702],"iteration":233,"passed_time":0.1257733658,"remaining_time":0.4117196504},
{"learn":[4.664241291],"iteration":234,"passed_time":0.1260281363,"remaining_time":0.4102618054},
{"learn":[4.662246999],"iteration":235,"passed_time":0.1262987779,"remaining_time":0.4088655353},
{"learn":[4.658668443],"iteration":236,"passed_time":0.1265480498,"remaining_time":0.4074099662},
{"learn":[4.658017572],"iteration":237,"passed_time":0.1268202743,"remaining_time":0.4060380212},
{"learn":[4.657656705],"iteration":238,"passed_time":0.1270802519,"remaining_time":0.4046362833},
{"learn":[4.653242871],"iteration":239,"passed_time":0.1273618491,"remaining_time":0.4033125223},
{"learn":[4.6507302],"iteration":240,"passed_time":0.1276485285,"remaining_time":0.4020134154},
{"learn":[4.647671336],"iteration":241,"passed_time":0.1279206697,"remaining_time":0.400677139},
{"learn":[4.645506007],"iteration":242,"passed_time":0.1282026419,"remaining_time":0.3993802464},
{"learn":[4.641297906],"iteration":243,"passed_time":0.1284465817,"remaining_time":0.3979738351},
{"learn":[4.63798107],"iteration":244,"passed_time":0.1287361353,"remaining_time":0.3967174782},
{"learn":[4.635062318],"iteration":245,"passed_time":0.1290039026,"remaining_time":0.3954022056},
{"learn":[4.631606017],"iteration":246,"passed_time":0.1293417777,"remaining_time":0.3943091441},
{"learn":[4.630215494],"iteration":247,"passed_time":0.1296288736,"remaining_time":0.3930681972},
{"learn":[4.62729814],"iteration":248,"passed_time":0.1299869936,"remaining_time":0.3920491252},
{"learn":[4.624691756],"iteration":249,"passed_time":0.130289544,"remaining_time":0.390868632},
{"learn":[4.621840053],"iteration":250,"passed_time":0.1306121728,"remaining_time":0.3897550495},
{"learn":[4.619602091],"iteration":251,"passed_time":0.1308576123,"remaining_time":0.3884186269},
{"learn":[4.613584029],"iteration":252,"passed_time":0.1312139411,"remaining_time":0.3874182371},
{"learn":[4.6119388],"iteration":253,"passed_time":0.1315496916,"remaining_time":0.3863624802},
{"learn":[4.60870702],"iteration":254,"passed_time":0.1319025213,"remaining_time":0.3853622682},
{"learn":[4.604771557],"iteration":255,"passed_time":0.1321650399,"remaining_time":0.3841046473},
{"learn":[4.604231277],"iteration":256,"passed_time":0.1324358898,"remaining_time":0.3828788566},
{"learn":[4.600750354],"iteration":257,"passed_time":0.132736649,"remaining_time":0.3817464867},
{"learn":[4.596488253],"iteration":258,"passed_time":0.1331373419,"remaining_time":0.3809064492},
{"learn":[4.59470784],"iteration":259,"passed_time":0.1335454496,"remaining_time":0.380090895},
{"learn":[4.588818005],"iteration":260,"passed_time":0.1339111928,"remaining_time":0.3791585113},
{"learn":[4.585054174],"iteration":261,"passed_time":0.1342253653,"remaining_time":0.3780851893},
{"learn":[4.581471435],"iteration":262,"passed_time":0.1345253747,"remaining_time":0.376977951},
{"learn":[4.577555199],"iteration":263,"passed_time":0.1348317158,"remaining_time":0.3758944804},
{"learn":[4.57457145],"iteration":264,"passed_time":0.1351820044,"remaining_time":0.374938767},
{"learn":[4.573029224],"iteration":265,"passed_time":0.1354809307,"remaining_time":0.3738458765},
{"learn":[4.571326203],"iteration":266,"passed_time":0.1358619201,"remaining_time":0.3729842227},
{"learn":[4.571019224],"iteration":267,"passed_time":0.1362075433,"remaining_time":0.3720295585},
{"learn":[4.565766631],"iteration":268,"passed_time":0.1364818923,"remaining_time":0.370885737},
{"learn":[4.563383471],"iteration":269,"passed_time":0.1367299561,"remaining_time":0.3696772888},
{"learn":[4.558165805],"iteration":270,"passed_time":0.1369838102,"remaining_time":0.3684915042},
{"learn":[4.55629209],"iteration":271,"passed_time":0.1372755299,"remaining_time":0.3674139184},
{"learn":[4.549383848],"iteration":272,"passed_time":0.1375602514,"remaining_time":0.3663234534},
{"learn":[4.546227503],"iteration":273,"passed_time":0.137903875,"remaining_time":0.365394939},
{"learn":[4.540620977],"iteration":274,"passed_time":0.1381832228,"remaining_time":0.3643012238},
{"learn":[4.532898237],"iteration":275,"passed_time":0.1384378684,"remaining_time":0.3631486112},
{"learn":[4.529757367],"iteration":276,"passed_time":0.1386793505,"remaining_time":0.3619681242},
{"learn":[4.52579294],"iteration":277,"passed_time":0.1390122684,"remaining_time":0.3610318626},
{"learn":[4.521572155],"iteration":278,"passed_time":0.1392772448,"remaining_time":0.3599243494},
{"learn":[4.518818099],"iteration":279,"passed_time":0.1396002068,"remaining_time":0.3589719604},
{"learn":[4.514012334],"iteration":280,"passed_time":0.1398657247,"remaining_time":0.3578770678},
{"learn":[4.508331416],"iteration":281,"passed_time":0.1401651925,"remaining_time":0.3568744972},
{"learn":[4.506038537],"iteration":282,"passed_time":0.1404789485,"remaining_time":0.3559130956},
{"learn":[4.505805643],"iteration":283,"passed_time":0.1407916631,"remaining_time":0.3549536294},
{"learn":[4.501550352],"iteration":284,"passed_time":0.1410810917,"remaining_time":0.3539402827},
{"learn":[4.494692643],"iteration":285,"passed_time":0.1414197165,"remaining_time":0.3530548168},
{"learn":[4.489330245],"iteration":286,"passed_time":0.1418038302,"remaining_time":0.3522861704},
{"learn":[4.484826955],"iteration":287,"passed_time":0.1421385393,"remaining_time":0.3513980555},
{"learn":[4.478285428],"iteration":288,"passed_time":0.1423841454,"remaining_time":0.3502945585},
{"learn":[4.475311671],"iteration":289,"passed_time":0.1426585778,"remaining_time":0.3492675525},
{"learn":[4.471581298],"iteration":290,"passed_time":0.1429904126,"remaining_time":0.3483855758},
{"learn":[4.469164956],"iteration":291,"passed_time":0.1432830071,"remaining_time":0.3474122228},
{"learn":[4.462068024],"iteration":292,"passed_time":0.1436042613,"remaining_time":0.3465126714},
{"learn":[4.458540976],"iteration":293,"passed_time":0.1439234326,"remaining_time":0.3456120524},
{"learn":[4.455757458],"iteration":294,"passed_time":0.1442383133,"remaining_time":0.3447051216},
{"learn":[4.453027414],"iteration":295,"passed_time":0.1445482369,"remaining_time":0.3437904012},
{"learn":[4.450659338],"iteration":296,"passed_time":0.1449255605,"remaining_time":0.3430392897},
{"learn":[4.444696901],"iteration":297,"passed_time":0.1452267779,"remaining_time":0.342111403},
{"learn":[4.442052813],"iteration":298,"passed_time":0.1458426677,"remaining_time":0.3419254518},
{"learn":[4.440036756],"iteration":299,"passed_time":0.1462408612,"remaining_time":0.3412286762},
{"learn":[4.435017051],"iteration":300,"passed_time":0.1465831518,"remaining_time":0.3404040636},
{"learn":[4.429962125],"iteration":301,"passed_time":0.1469096547,"remaining_time":0.3395461555},
{"learn":[4.427666256],"iteration":302,"passed_time":0.1471661331,"remaining_time":0.3385306758},
{"learn":[4.425030004],"iteration":303,"passed_time":0.1474311928,"remaining_time":0.337539836},
{"learn":[4.422588771],"iteration":304,"passed_time":0.1477602366,"remaining_time":0.3366995556},
{"learn":[4.418936667],"iteration":305,"passed_time":0.1481270629,"remaining_time":0.335948306},
{"learn":[4.416887976],"iteration":306,"passed_time":0.1484264057,"remaining_time":0.3350472285},
{"learn":[4.413773354],"iteration":307,"passed_time":0.1487015462,"remaining_time":0.3340956818},
{"learn":[4.411129391],"iteration":308,"passed_time":0.1490108866,"remaining_time":0.3332249924},
{"learn":[4.40850819],"iteration":309,"passed_time":0.149359509,"remaining_time":0.3324453587},
{"learn":[4.404880292],"iteration":310,"passed_time":0.1496356909,"remaining_time":0.3315080098},
{"learn":[4.404593827],"iteration":311,"passed_time":0.1499298684,"remaining_time":0.3306145815},
{"learn":[4.402139942],"iteration":312,"passed_time":0.1501634358,"remaining_time":0.3295919501},
{"learn":[4.400284725],"iteration":313,"passed_time":0.15045728,"remaining_time":0.3287060321},
{"learn":[4.395805521],"iteration":314,"passed_time":0.150791406,"remaining_time":0.3279114701},
{"learn":[4.392838833],"iteration":315,"passed_time":0.1511685213,"remaining_time":0.3272128753},
{"learn":[4.389213061],"iteration":316,"passed_time":0.1515347227,"remaining_time":0.3264927937},
{"learn":[4.3861981],"iteration":317,"passed_time":0.1518154452,"remaining_time":0.3255916151},
{"learn":[4.385054234],"iteration":318,"passed_time":0.152101458,"remaining_time":0.3247056203},
{"learn":[4.379364607],"iteration":319,"passed_time":0.1524091321,"remaining_time":0.3238694057},
{"learn":[4.378387619],"iteration":320,"passed_time":0.1527028097,"remaining_time":0.3230068779},
{"learn":[4.375816727],"iteration":321,"passed_time":0.1530099423,"remaining_time":0.322176214},
{"learn":[4.374600202],"iteration":322,"passed_time":0.1533930979,"remaining_time":0.3215081339},
{"learn":[4.37098897],"iteration":323,"passed_time":0.1536827764,"remaining_time":0.3206467805},
{"learn":[4.367418484],"iteration":324,"passed_time":0.153975371,"remaining_time":0.3197950012},
{"learn":[4.363584638],"iteration":325,"passed_time":0.1543231602,"remaining_time":0.3190607668},
{"learn":[4.360770706],"iteration":326,"passed_time":0.1546236695,"remaining_time":0.3182315888},
{"learn":[4.358675808],"iteration":327,"passed_time":0.1549409662,"remaining_time":0.3174400284},
{"learn":[4.354228195],"iteration":328,"passed_time":0.155296212,"remaining_time":0.3167287484},
{"learn":[4.353773425],"iteration":329,"passed_time":0.1555721439,"remaining_time":0.3158585953},
{"learn":[4.351648009],"iteration":330,"passed_time":0.1558718617,"remaining_time":0.3150401072},
{"learn":[4.348209927],"iteration":331,"passed_time":0.1562414789,"remaining_time":0.3143653853},
{"learn":[4.345852733],"iteration":332,"passed_time":0.1565159113,"remaining_time":0.3135018403},
{"learn":[4.34237339],"iteration":333,"passed_time":0.1567500202,"remaining_time":0.3125614175},
{"learn":[4.340814362],"iteration":334,"passed_time":0.1570266603,"remaining_time":0.3117096392},
{"learn":[4.339707068],"iteration":335,"passed_time":0.1572719332,"remaining_time":0.3107992966},
{"learn":[4.335430786],"iteration":336,"passed_time":0.1576251794,"remaining_time":0.3101053234},
{"learn":[4.33521887],"iteration":337,"passed_time":0.157993547,"remaining_time":0.3094429825},
{"learn":[4.328507238],"iteration":338,"passed_time":0.1583863668,"remaining_time":0.3088300544},
{"learn":[4.326140732],"iteration":339,"passed_time":0.1587278243,"remaining_time":0.3081187177},
{"learn":[4.323785636],"iteration":340,"passed_time":0.1590579095,"remaining_time":0.307387573},
{"learn":[4.320632534],"iteration":341,"passed_time":0.159427735,"remaining_time":0.3067352329},
{"learn":[4.31973724],"iteration":342,"passed_time":0.1596809226,"remaining_time":0.3058611258},
{"learn":[4.318000924],"iteration":343,"passed_time":0.1599819317,"remaining_time":0.3050818233},
{"learn":[4.312713628],"iteration":344,"passed_time":0.1602766924,"remaining_time":0.3042934305},
{"learn":[4.308220789],"iteration":345,"passed_time":0.1605737858,"remaining_time":0.3035123003},
{"learn":[4.305890947],"iteration":346,"passed_time":0.1608430527,"remaining_time":0.3026815949},
{"learn":[4.305137856],"iteration":347,"passed_time":0.1611479776,"remaining_time":0.3019209235},
{"learn":[4.304787172],"iteration":348,"passed_time":0.1614673988,"remaining_time":0.3011899044},
{"learn":[4.30350134],"iteration":349,"passed_time":0.1617311255,"remaining_time":0.3003578044},
{"learn":[4.30293809],"iteration":350,"passed_time":0.1621122815,"remaining_time":0.2997460703},
{"learn":[4.299548459],"iteration":351,"passed_time":0.1624995193,"remaining_time":0.2991468424},
{"learn":[4.294768408],"iteration":352,"passed_time":0.1627487496,"remaining_time":0.2982958668},
{"learn":[4.294581479],"iteration":353,"passed_time":0.1630211824,"remaining_time":0.2974906323},
{"learn":[4.292551604],"iteration":354,"passed_time":0.1632761195,"remaining_time":0.2966566116},
{"learn":[4.288628894],"iteration":355,"passed_time":0.1635513434,"remaining_time":0.2958625425},
{"learn":[4.287802767],"iteration":356,"passed_time":0.1638436463,"remaining_time":0.2951021416},
{"learn":[4.284566905],"iteration":357,"passed_time":0.1641691494,"remaining_time":0.2944038936},
{"learn":[4.27890232],"iteration":358,"passed_time":0.1644903202,"remaining_time":0.2936999867},
{"learn":[4.276938023],"iteration":359,"passed_time":0.164807492,"remaining_time":0.2929910969},
{"learn":[4.273425094],"iteration":360,"passed_time":0.1650904639,"remaining_time":0.2922238405},
{"learn":[4.269726505],"iteration":361,"passed_time":0.1653885987,"remaining_time":0.2914859834},
{"learn":[4.265565857],"iteration":362,"passed_time":0.1656798602,"remaining_time":0.2907384875},
{"learn":[4.262117173],"iteration":363,"passed_time":0.1660114868,"remaining_time":0.2900640264},
{"learn":[4.259185148],"iteration":364,"passed_time":0.1664250099,"remaining_time":0.2895339213},
{"learn":[4.257668507],"iteration":365,"passed_time":0.1667872122,"remaining_time":0.2889155534},
{"learn":[4.253432436],"iteration":366,"passed_time":0.1671027594,"remaining_time":0.2882181109},
{"learn":[4.250216667],"iteration":367,"passed_time":0.1673464493,"remaining_time":0.2873993369},
{"learn":[4.24514828],"iteration":368,"passed_time":0.1676212566,"remaining_time":0.2866368914},
{"learn":[4.244015772],"iteration":369,"passed_time":0.1679721284,"remaining_time":0.286006597},
{"learn":[4.240329192],"iteration":370,"passed_time":0.1682604323,"remaining_time":0.2852717303},
{"learn":[4.236718014],"iteration":371,"passed_time":0.1686208018,"remaining_time":0.2846609235},
{"learn":[4.233495944],"iteration":372,"passed_time":0.1689594683,"remaining_time":0.2840149776},
{"learn":[4.230357491],"iteration":373,"passed_time":0.1692428151,"remaining_time":0.2832780809},
{"learn":[4.227381215],"iteration":374,"passed_time":0.1694992519,"remaining_time":0.2824987532},
{"learn":[4.226169067],"iteration":375,"passed_time":0.1698972788,"remaining_time":0.2819571861},
{"learn":[4.225963861],"iteration":376,"passed_time":0.1701439263,"remaining_time":0.281166223},
{"learn":[4.224346548],"iteration":377,"passed_time":0.1704166924,"remaining_time":0.2804211182},
{"learn":[4.222595381],"iteration":378,"passed_time":0.1707016221,"remaining_time":0.2796984363},
{"learn":[4.219700938],"iteration":379,"passed_time":0.1710675319,"remaining_time":0.2791101837},
{"learn":[4.216356207],"iteration":380,"passed_time":0.1714131967,"remaining_time":0.2784902067},
{"learn":[4.214326494],"iteration":381,"passed_time":0.1717347841,"remaining_time":0.2778327135},
{"learn":[4.212901398],"iteration":382,"passed_time":0.1721044013,"remaining_time":0.2772543488},
{"learn":[4.211331091],"iteration":383,"passed_time":0.1724456921,"remaining_time":0.2766316311},
{"learn":[4.208624791],"iteration":384,"passed_time":0.1726933394,"remaining_time":0.2758607889},
{"learn":[4.204659106],"iteration":385,"passed_time":0.1729643976,"remaining_time":0.2751298967},
{"learn":[4.202968852],"iteration":386,"passed_time":0.1732628657,"remaining_time":0.2744447976},
{"learn":[4.197261935],"iteration":387,"passed_time":0.1735746221,"remaining_time":0.2737826514},
{"learn":[4.196934403],"iteration":388,"passed_time":0.1738865452,"remaining_time":0.2731225685},
{"learn":[4.192479929],"iteration":389,"passed_time":0.1741683508,"remaining_time":0.272417164},
{"learn":[4.190243116],"iteration":390,"passed_time":0.1745680855,"remaining_time":0.2718976064},
{"learn":[4.185852431],"iteration":391,"passed_time":0.1749072519,"remaining_time":0.2712847172},
{"learn":[4.180967944],"iteration":392,"passed_time":0.1752291725,"remaining_time":0.2706465846},
{"learn":[4.178283162],"iteration":393,"passed_time":0.1754882753,"remaining_time":0.2699134387},
{"learn":[4.176341157],"iteration":394,"passed_time":0.1757267999,"remaining_time":0.2691511745},
{"learn":[4.176041504],"iteration":395,"passed_time":0.176019561,"remaining_time":0.2684742799},
{"learn":[4.175564513],"iteration":396,"passed_time":0.176346647,"remaining_time":0.2678514563},
{"learn":[4.170830274],"iteration":397,"passed_time":0.1766702339,"remaining_time":0.2672248262},
{"learn":[4.167804808],"iteration":398,"passed_time":0.1769434582,"remaining_time":0.2665238556},
{"learn":[4.165860548],"iteration":399,"passed_time":0.1772819998,"remaining_time":0.2659229996},
{"learn":[4.160950571],"iteration":400,"passed_time":0.177581176,"remaining_time":0.2652646494},
{"learn":[4.158544115],"iteration":401,"passed_time":0.177840612,"remaining_time":0.2645489701},
{"learn":[4.154448767],"iteration":402,"passed_time":0.1781232507,"remaining_time":0.2638699272},
{"learn":[4.15197457],"iteration":403,"passed_time":0.1783457791,"remaining_time":0.2631041692},
{"learn":[4.149562679],"iteration":404,"passed_time":0.178593843,"remaining_time":0.2623786088},
{"learn":[4.149327961],"iteration":405,"passed_time":0.1788216202,"remaining_time":0.2616257201},
{"learn":[4.147444889],"iteration":406,"passed_time":0.1790513135,"remaining_time":0.2608782037},
{"learn":[4.147254809],"iteration":407,"passed_time":0.1792748418,"remaining_time":0.2601242802},
{"learn":[4.144589165],"iteration":408,"passed_time":0.1795447752,"remaining_time":0.2594400052},
{"learn":[4.141691034],"iteration":409,"passed_time":0.1798375364,"remaining_time":0.2587906011},
{"learn":[4.138893468],"iteration":410,"passed_time":0.1800839339,"remaining_time":0.2580764893},
{"learn":[4.136964597],"iteration":411,"passed_time":0.1803424535,"remaining_time":0.2573819483},
{"learn":[4.133773523],"iteration":412,"passed_time":0.1806028477,"remaining_time":0.256692183},
{"learn":[4.131363444],"iteration":413,"passed_time":0.1808726561,"remaining_time":0.2560178176},
{"learn":[4.130228592],"iteration":414,"passed_time":0.1811209283,"remaining_time":0.2553150435},
{"learn":[4.12884186],"iteration":415,"passed_time":0.1813718664,"remaining_time":0.2546181971},
{"learn":[4.12413494],"iteration":416,"passed_time":0.1816465903,"remaining_time":0.2539567438},
{"learn":[4.119422508],"iteration":417,"passed_time":0.1819037769,"remaining_time":0.2532727229},
{"learn":[4.117038244],"iteration":418,"passed_time":0.1821540069,"remaining_time":0.2525810931},
{"learn":[4.116067631],"iteration":419,"passed_time":0.1823898238,"remaining_time":0.2518716614},
{"learn":[4.110343455],"iteration":420,"passed_time":0.1826271403,"remaining_time":0.2511665421},
{"learn":[4.105604544],"iteration":421,"passed_time":0.1828535844,"remaining_time":0.2504487483},
{"learn":[4.103390131],"iteration":422,"passed_time":0.183102648,"remaining_time":0.2497641322},
{"learn":[4.096724402],"iteration":423,"passed_time":0.1833397146,"remaining_time":0.2490652726},
{"learn":[4.093431279],"iteration":424,"passed_time":0.1835593271,"remaining_time":0.2483449719},
{"learn":[4.091412744],"iteration":425,"passed_time":0.1838061412,"remaining_time":0.2476636739},
{"learn":[4.091192901],"iteration":426,"passed_time":0.1840429579,"remaining_time":0.246970995},
{"learn":[4.088994581],"iteration":427,"passed_time":0.1842797745,"remaining_time":0.2462804462},
{"learn":[4.087845355],"iteration":428,"passed_time":0.1844974708,"remaining_time":0.2455665637},
{"learn":[4.083650279],"iteration":429,"passed_time":0.1847289554,"remaining_time":0.2448732664},
{"learn":[4.079840652],"iteration":430,"passed_time":0.18498735,"remaining_time":0.2442176384},
{"learn":[4.075707828],"iteration":431,"passed_time":0.1852210841,"remaining_time":0.2435314253},
{"learn":[4.071345409],"iteration":432,"passed_time":0.1854675649,"remaining_time":0.2428639938},
{"learn":[4.067460475],"iteration":433,"passed_time":0.1857143791,"remaining_time":0.2421989368},
{"learn":[4.064914749],"iteration":434,"passed_time":0.1859605684,"remaining_time":0.2415349911},
{"learn":[4.063823175],"iteration":435,"passed_time":0.1861999261,"remaining_time":0.2408641245},
{"learn":[4.058898471],"iteration":436,"passed_time":0.1864392837,"remaining_time":0.2401952328},
{"learn":[4.054120355],"iteration":437,"passed_time":0.1866808075,"remaining_time":0.2395310818},
{"learn":[4.052715901],"iteration":438,"passed_time":0.186908668,"remaining_time":0.2388513958},
{"learn":[4.052114167],"iteration":439,"passed_time":0.187139986,"remaining_time":0.2381781639},
{"learn":[4.051377267],"iteration":440,"passed_time":0.1873804267,"remaining_time":0.2375185},
{"learn":[4.049275336],"iteration":441,"passed_time":0.1875938324,"remaining_time":0.2368266029},
{"learn":[4.047099198],"iteration":442,"passed_time":0.1878353978,"remaining_time":0.2361722722},
{"learn":[4.044348685],"iteration":443,"passed_time":0.1881287422,"remaining_time":0.2355846411},
{"learn":[4.042822379],"iteration":444,"passed_time":0.1883921772,"remaining_time":0.23496103},
{"learn":[4.041258611],"iteration":445,"passed_time":0.1886644018,"remaining_time":0.234349952},
{"learn":[4.040044254],"iteration":446,"passed_time":0.1889436663,"remaining_time":0.2337490994},
{"learn":[4.036860137],"iteration":447,"passed_time":0.1892217644,"remaining_time":0.2331482454},
{"learn":[4.036372284],"iteration":448,"passed_time":0.1894783261,"remaining_time":0.2325224002},
{"learn":[4.03368231],"iteration":449,"passed_time":0.1897250569,"remaining_time":0.2318861807},
{"learn":[4.032439519],"iteration":450,"passed_time":0.1899607072,"remaining_time":0.2312382001},
{"learn":[4.032008634],"iteration":451,"passed_time":0.1902250587,"remaining_time":0.230626841},
{"learn":[4.030034932],"iteration":452,"passed_time":0.1904677905,"remaining_time":0.2299909082},
{"learn":[4.028173412],"iteration":453,"passed_time":0.1907201866,"remaining_time":0.2293683301},
{"learn":[4.023806097],"iteration":454,"passed_time":0.190969875,"remaining_time":0.228744136},
{"learn":[4.020239186],"iteration":455,"passed_time":0.1912185637,"remaining_time":0.2281203918},
{"learn":[4.017384838],"iteration":456,"passed_time":0.1914762918,"remaining_time":0.2275090295},
{"learn":[4.016468229],"iteration":457,"passed_time":0.191719107,"remaining_time":0.2268815633},
{"learn":[4.014530169],"iteration":458,"passed_time":0.1919792095,"remaining_time":0.2262761489},
{"learn":[4.012884822],"iteration":459,"passed_time":0.192224524,"remaining_time":0.225654876},
{"learn":[4.008924707],"iteration":460,"passed_time":0.1924618405,"remaining_time":0.225025883},
{"learn":[4.008286778],"iteration":461,"passed_time":0.1927021979,"remaining_time":0.2244021266},
{"learn":[4.006444202],"iteration":462,"passed_time":0.1929582598,"remaining_time":0.2237982408},
{"learn":[4.003284363],"iteration":463,"passed_time":0.1932219448,"remaining_time":0.2232046604},
{"learn":[3.999811484],"iteration":464,"passed_time":0.193474091,"remaining_time":0.2225992229},
{"learn":[3.997483319],"iteration":465,"passed_time":0.1937491481,"remaining_time":0.222021556},
{"learn":[3.99708333],"iteration":466,"passed_time":0.1939797579,"remaining_time":0.2213944561},
{"learn":[3.995860263],"iteration":467,"passed_time":0.1942400271,"remaining_time":0.2208027659},
{"learn":[3.994131111],"iteration":468,"passed_time":0.194474386,"remaining_time":0.2201831534},
{"learn":[3.993125499],"iteration":469,"passed_time":0.1947707296,"remaining_time":0.2196350781},
{"learn":[3.992954084],"iteration":470,"passed_time":0.1950459951,"remaining_time":0.2190643979},
{"learn":[3.990635743],"iteration":471,"passed_time":0.1952925593,"remaining_time":0.2184628629},
{"learn":[3.986678254],"iteration":472,"passed_time":0.1955344996,"remaining_time":0.2178576772},
{"learn":[3.986393291],"iteration":473,"passed_time":0.1957556534,"remaining_time":0.2172309572},
{"learn":[3.986152671],"iteration":474,"passed_time":0.196007633,"remaining_time":0.2166400154},
{"learn":[3.985596662],"iteration":475,"passed_time":0.1962551553,"remaining_time":0.2160455911},
{"learn":[3.983853457],"iteration":476,"passed_time":0.1964939714,"remaining_time":0.2154430756},
{"learn":[3.983263928],"iteration":477,"passed_time":0.1967236648,"remaining_time":0.2148321193},
{"learn":[3.980067202],"iteration":478,"passed_time":0.1969634807,"remaining_time":0.214233765},
{"learn":[3.978115407],"iteration":479,"passed_time":0.1971990059,"remaining_time":0.2136322564},
{"learn":[3.972661644],"iteration":480,"passed_time":0.1974462366,"remaining_time":0.2130448998},
{"learn":[3.969938254],"iteration":481,"passed_time":0.1977198358,"remaining_time":0.2124872925},
{"learn":[3.968211434],"iteration":482,"passed_time":0.1979536948,"remaining_time":0.2118883235},
{"learn":[3.966113368],"iteration":483,"passed_time":0.198229002,"remaining_time":0.2113350517},
{"learn":[3.962246044],"iteration":484,"passed_time":0.1984689012,"remaining_time":0.210745328},
{"learn":[3.961319703],"iteration":485,"passed_time":0.198713091,"remaining_time":0.2101615818},
{"learn":[3.96078191],"iteration":486,"passed_time":0.1989422428,"remaining_time":0.2095633892},
{"learn":[3.958913633],"iteration":487,"passed_time":0.1991630217,"remaining_time":0.2089579244},
{"learn":[3.957428286],"iteration":488,"passed_time":0.1994072531,"remaining_time":0.2083785406},
{"learn":[3.952641965],"iteration":489,"passed_time":0.1996432366,"remaining_time":0.2077919402},
{"learn":[3.951486786],"iteration":490,"passed_time":0.1998932167,"remaining_time":0.2072212776},
{"learn":[3.94938344],"iteration":491,"passed_time":0.2001227018,"remaining_time":0.2066307571},
{"learn":[3.947297924],"iteration":492,"passed_time":0.2003771807,"remaining_time":0.2060674049},
{"learn":[3.946284886],"iteration":493,"passed_time":0.2006187045,"remaining_time":0.2054920333},
{"learn":[3.943288204],"iteration":494,"passed_time":0.2008560626,"remaining_time":0.2049137608},
{"learn":[3.943076488],"iteration":495,"passed_time":0.2010684686,"remaining_time":0.2043115084},
{"learn":[3.942347078],"iteration":496,"passed_time":0.2013301124,"remaining_time":0.203760657},
{"learn":[3.940251541],"iteration":497,"passed_time":0.2015578479,"remaining_time":0.2031767865},
{"learn":[3.939011019],"iteration":498,"passed_time":0.2017971223,"remaining_time":0.2026059284},
{"learn":[3.938760512],"iteration":499,"passed_time":0.2020261075,"remaining_time":0.2020261075},
{"learn":[3.934522727],"iteration":500,"passed_time":0.2022758376,"remaining_time":0.2014683492},
{"learn":[3.930091193],"iteration":501,"passed_time":0.2025252761,"remaining_time":0.2009115288},
{"learn":[3.927671752],"iteration":502,"passed_time":0.202764967,"remaining_time":0.2003462994},
{"learn":[3.927280041],"iteration":503,"passed_time":0.202978581,"remaining_time":0.1997566987},
{"learn":[3.925987561],"iteration":504,"passed_time":0.2032342263,"remaining_time":0.1992097862},
{"learn":[3.921645957],"iteration":505,"passed_time":0.2034790826,"remaining_time":0.1986534917},
{"learn":[3.920333743],"iteration":506,"passed_time":0.203747808,"remaining_time":0.1981216358},
{"learn":[3.918659461],"iteration":507,"passed_time":0.2039765016,"remaining_time":0.1975520449},
{"learn":[3.916124385],"iteration":508,"passed_time":0.2042144846,"remaining_time":0.1969927543},
{"learn":[3.913849268],"iteration":509,"passed_time":0.2044362632,"remaining_time":0.1964191549},
{"learn":[3.912826119],"iteration":510,"passed_time":0.204683244,"remaining_time":0.1958710496},
{"learn":[3.910034145],"iteration":511,"passed_time":0.2049096465,"remaining_time":0.1953045069},
{"learn":[3.90792379],"iteration":512,"passed_time":0.2051734148,"remaining_time":0.1947747622},
{"learn":[3.907823851],"iteration":513,"passed_time":0.2054370165,"remaining_time":0.194245895},
{"learn":[3.904527401],"iteration":514,"passed_time":0.2056575871,"remaining_time":0.1936775335},
{"learn":[3.903378283],"iteration":515,"passed_time":0.2059282287,"remaining_time":0.1931574859},
{"learn":[3.902170135],"iteration":516,"passed_time":0.2061736682,"remaining_time":0.1926148583},
{"learn":[3.899435429],"iteration":517,"passed_time":0.2064196076,"remaining_time":0.1920738434},
{"learn":[3.897497505],"iteration":518,"passed_time":0.2066618812,"remaining_time":0.1915305681},
{"learn":[3.896426119],"iteration":519,"passed_time":0.2069011972,"remaining_time":0.1909857205},
{"learn":[3.896044669],"iteration":520,"passed_time":0.2071473865,"remaining_time":0.1904483649},
{"learn":[3.892795942],"iteration":521,"passed_time":0.2073776214,"remaining_time":0.1898975154},
{"learn":[3.892413888],"iteration":522,"passed_time":0.2076121053,"remaining_time":0.1893517671},
{"learn":[3.891738985],"iteration":523,"passed_time":0.2078541706,"remaining_time":0.1888140939},
{"learn":[3.88822057],"iteration":524,"passed_time":0.2080854885,"remaining_time":0.188267823},
{"learn":[3.883837053],"iteration":525,"passed_time":0.2083268457,"remaining_time":0.1877317963},
{"learn":[3.881769742],"iteration":526,"passed_time":0.2085685778,"remaining_time":0.1871972244},
{"learn":[3.880356898],"iteration":527,"passed_time":0.2088092684,"remaining_time":0.1866628309},
{"learn":[3.879250273],"iteration":528,"passed_time":0.20903263,"remaining_time":0.1861141186},
{"learn":[3.877174493],"iteration":529,"passed_time":0.2092676138,"remaining_time":0.1855769405},
{"learn":[3.875854201],"iteration":530,"passed_time":0.2095040971,"remaining_time":0.1850422251},
{"learn":[3.873189396],"iteration":531,"passed_time":0.209768282,"remaining_time":0.1845329999},
{"learn":[3.871583368],"iteration":532,"passed_time":0.2099963091,"remaining_time":0.1839930138},
{"learn":[3.869622679],"iteration":533,"passed_time":0.2102346253,"remaining_time":0.1834631749},
{"learn":[3.866860164],"iteration":534,"passed_time":0.2104558208,"remaining_time":0.1829195452},
{"learn":[3.864498444],"iteration":535,"passed_time":0.2107088834,"remaining_time":0.182404705},
{"learn":[3.861416322],"iteration":536,"passed_time":0.2109424925,"remaining_time":0.1818740671},
{"learn":[3.860265769],"iteration":537,"passed_time":0.2111974296,"remaining_time":0.1813628485},
{"learn":[3.859328725],"iteration":538,"passed_time":0.2114478679,"remaining_time":0.180848733},
{"learn":[3.858521278],"iteration":539,"passed_time":0.2116958484,"remaining_time":0.1803335005},
{"learn":[3.85599111],"iteration":540,"passed_time":0.2119236256,"remaining_time":0.1798021149},
{"learn":[3.852379816],"iteration":541,"passed_time":0.2121739389,"remaining_time":0.179290893},
{"learn":[3.851327537],"iteration":542,"passed_time":0.2124216278,"remaining_time":0.1787784234},
{"learn":[3.847854898],"iteration":543,"passed_time":0.2126393658,"remaining_time":0.1782418213},
{"learn":[3.847083414],"iteration":544,"passed_time":0.2129176722,"remaining_time":0.1777569557},
{"learn":[3.845397429],"iteration":545,"passed_time":0.2131291617,"remaining_time":0.1772172883},
{"learn":[3.841933528],"iteration":546,"passed_time":0.2133958043,"remaining_time":0.1767244961},
{"learn":[3.840996474],"iteration":547,"passed_time":0.2136634883,"remaining_time":0.1762333882},
{"learn":[3.838355966],"iteration":548,"passed_time":0.2139035958,"remaining_time":0.1757204402},
{"learn":[3.83342799],"iteration":549,"passed_time":0.214159491,"remaining_time":0.1752214017},
{"learn":[3.828161535],"iteration":550,"passed_time":0.214454335,"remaining_time":0.1747549844},
{"learn":[3.823502399],"iteration":551,"passed_time":0.2147088556,"remaining_time":0.1742564625},
{"learn":[3.820068862],"iteration":552,"passed_time":0.2149552948,"remaining_time":0.1737522907},
{"learn":[3.817951642],"iteration":553,"passed_time":0.2151904452,"remaining_time":0.1732399613},
{"learn":[3.815785958],"iteration":554,"passed_time":0.2154561297,"remaining_time":0.172753113},
{"learn":[3.81503012],"iteration":555,"passed_time":0.2156737427,"remaining_time":0.1722286722},
{"learn":[3.813529315],"iteration":556,"passed_time":0.2159273052,"remaining_time":0.1717339249},
{"learn":[3.808881326],"iteration":557,"passed_time":0.2161750774,"remaining_time":0.1712354556},
{"learn":[3.808740434],"iteration":558,"passed_time":0.2164181425,"remaining_time":0.1707341696},
{"learn":[3.80714352],"iteration":559,"passed_time":0.2166416707,"remaining_time":0.1702184555},
{"learn":[3.80573346],"iteration":560,"passed_time":0.2168973993,"remaining_time":0.1697289809},
{"learn":[3.803370052],"iteration":561,"passed_time":0.2171598763,"remaining_time":0.1692455975},
{"learn":[3.803215211],"iteration":562,"passed_time":0.2173976926,"remaining_time":0.1687438573},
{"learn":[3.801309667],"iteration":563,"passed_time":0.2176509635,"remaining_time":0.1682550002},
{"learn":[3.800003847],"iteration":564,"passed_time":0.2178947368,"remaining_time":0.1677596646},
{"learn":[3.798026138],"iteration":565,"passed_time":0.2181333446,"remaining_time":0.1672612572},
{"learn":[3.794745847],"iteration":566,"passed_time":0.2183817,"remaining_time":0.1667712101},
{"learn":[3.794312041],"iteration":567,"passed_time":0.2186490508,"remaining_time":0.1662964612},
{"learn":[3.792205926],"iteration":568,"passed_time":0.2188974895,"remaining_time":0.165808116},
{"learn":[3.788991061],"iteration":569,"passed_time":0.2191456783,"remaining_time":0.165320424},
{"learn":[3.787391572],"iteration":570,"passed_time":0.2193972413,"remaining_time":0.164836106},
{"learn":[3.7826445],"iteration":571,"passed_time":0.2196452218,"remaining_time":0.1643499212},
{"learn":[3.781700331],"iteration":572,"passed_time":0.2198909113,"remaining_time":0.1638628606},
{"learn":[3.780045374],"iteration":573,"passed_time":0.2201235206,"remaining_time":0.1633669334},
{"learn":[3.775462644],"iteration":574,"passed_time":0.2203747503,"remaining_time":0.162885685},
{"learn":[3.773711943],"iteration":575,"passed_time":0.2206101089,"remaining_time":0.1623935524},
{"learn":[3.772415806],"iteration":576,"passed_time":0.2208898316,"remaining_time":0.1619348333},
{"learn":[3.770170875],"iteration":577,"passed_time":0.2211371873,"remaining_time":0.1614531022},
{"learn":[3.765166479],"iteration":578,"passed_time":0.2213805857,"remaining_time":0.1609693032},
{"learn":[3.763976102],"iteration":579,"passed_time":0.2216307323,"remaining_time":0.16049122},
{"learn":[3.760761708],"iteration":580,"passed_time":0.221859051,"remaining_time":0.1599981797},
{"learn":[3.758155662],"iteration":581,"passed_time":0.2221168625,"remaining_time":0.1595272311},
{"learn":[3.756844548],"iteration":582,"passed_time":0.2223858378,"remaining_time":0.1590649989},
{"learn":[3.753098923],"iteration":583,"passed_time":0.2226170725,"remaining_time":0.1585765448},
{"learn":[3.751618946],"iteration":584,"passed_time":0.2228590961,"remaining_time":0.1580966238},
{"learn":[3.751398464],"iteration":585,"passed_time":0.2230977456,"remaining_time":0.1576151309},
{"learn":[3.749920103],"iteration":586,"passed_time":0.2233968386,"remaining_time":0.157176992},
{"learn":[3.748237465],"iteration":587,"passed_time":0.2236311558,"remaining_time":0.1566939391},
{"learn":[3.746021536],"iteration":588,"passed_time":0.2238655147,"remaining_time":0.1562117598},
{"learn":[3.74417648],"iteration":589,"passed_time":0.2241393222,"remaining_time":0.155757834},
{"learn":[3.738788389],"iteration":590,"passed_time":0.2243772635,"remaining_time":0.1552796967},
{"learn":[3.736021611],"iteration":591,"passed_time":0.2246197037,"remaining_time":0.1548054715},
{"learn":[3.734546151],"iteration":592,"passed_time":0.2248719332,"remaining_time":0.1543387467},
{"learn":[3.733527479],"iteration":593,"passed_time":0.2251317441,"remaining_time":0.1538779261},
{"learn":[3.733026392],"iteration":594,"passed_time":0.2253632704,"remaining_time":0.1533985286},
{"learn":[3.730314752],"iteration":595,"passed_time":0.2256145001,"remaining_time":0.1529333189},
{"learn":[3.727342596],"iteration":596,"passed_time":0.2258538161,"remaining_time":0.1524607837},
{"learn":[3.725459604],"iteration":597,"passed_time":0.2261170012,"remaining_time":0.1520050744},
{"learn":[3.723158842],"iteration":598,"passed_time":0.2263494439,"remaining_time":0.1515294274},
{"learn":[3.722362756],"iteration":599,"passed_time":0.2265911343,"remaining_time":0.1510607562},
{"learn":[3.721443615],"iteration":600,"passed_time":0.2268252433,"remaining_time":0.1505878071},
{"learn":[3.720743486],"iteration":601,"passed_time":0.2270558947,"remaining_time":0.1501133656},
{"learn":[3.720215334],"iteration":602,"passed_time":0.2273032504,"remaining_time":0.1496507304},
{"learn":[3.719436563],"iteration":603,"passed_time":0.2275608536,"remaining_time":0.1491955265},
{"learn":[3.715046574],"iteration":604,"passed_time":0.2277910468,"remaining_time":0.1487230802},
{"learn":[3.71443396],"iteration":605,"passed_time":0.2280404437,"remaining_time":0.1482639188},
{"learn":[3.712938941],"iteration":606,"passed_time":0.2283104604,"remaining_time":0.1478187989},
{"learn":[3.712814764],"iteration":607,"passed_time":0.2285773113,"remaining_time":0.1473722139},
{"learn":[3.71235348],"iteration":608,"passed_time":0.2288185852,"remaining_time":0.1469097977},
{"learn":[3.711223749],"iteration":609,"passed_time":0.2290537772,"remaining_time":0.1464442182},
{"learn":[3.710755648],"iteration":610,"passed_time":0.2293416229,"remaining_time":0.1460129154},
{"learn":[3.708668039],"iteration":611,"passed_time":0.2295990594,"remaining_time":0.1455628024},
{"learn":[3.705623591],"iteration":612,"passed_time":0.2299079832,"remaining_time":0.145145823},
{"learn":[3.704045802],"iteration":613,"passed_time":0.2301698353,"remaining_time":0.1446996033},
{"learn":[3.699915209],"iteration":614,"passed_time":0.230431021,"remaining_time":0.144253566},
{"learn":[3.696182221],"iteration":615,"passed_time":0.2306703369,"remaining_time":0.1437944958},
{"learn":[3.694263278],"iteration":616,"passed_time":0.2309247326,"remaining_time":0.1433454985},
{"learn":[3.693810229],"iteration":617,"passed_time":0.2311639236,"remaining_time":0.1428877327},
{"learn":[3.690900932],"iteration":618,"passed_time":0.2314010735,"remaining_time":0.1424294168},
{"learn":[3.688020895],"iteration":619,"passed_time":0.2316534279,"remaining_time":0.1419811332},
{"learn":[3.685491894],"iteration":620,"passed_time":0.2319021166,"remaining_time":0.1415312435},
{"learn":[3.684328128],"iteration":621,"passed_time":0.2321835889,"remaining_time":0.1411019238},
{"learn":[3.680640153],"iteration":622,"passed_time":0.2324159482,"remaining_time":0.1406433587},
{"learn":[3.678932783],"iteration":623,"passed_time":0.2326558058,"remaining_time":0.1401900368},
{"learn":[3.674167041],"iteration":624,"passed_time":0.2329409855,"remaining_time":0.1397645913},
{"learn":[3.672200976],"iteration":625,"passed_time":0.233210419,"remaining_time":0.1393301864},
{"learn":[3.670606604],"iteration":626,"passed_time":0.2334799776,"remaining_time":0.1388963822},
{"learn":[3.665506042],"iteration":627,"passed_time":0.2337205849,"remaining_time":0.1384459516},
{"learn":[3.664214007],"iteration":628,"passed_time":0.2339597343,"remaining_time":0.1379953282},
{"learn":[3.66261643],"iteration":629,"passed_time":0.234202841,"remaining_time":0.1375477003},
{"learn":[3.662118449],"iteration":630,"passed_time":0.2344600693,"remaining_time":0.1371089787},
{"learn":[3.660871366],"iteration":631,"passed_time":0.2347018013,"remaining_time":0.1366618084},
{"learn":[3.656695243],"iteration":632,"passed_time":0.2349662778,"remaining_time":0.1362284739},
{"learn":[3.654497801],"iteration":633,"passed_time":0.2352117589,"remaining_time":0.1357847063},
{"learn":[3.654189134],"iteration":634,"passed_time":0.2354429103,"remaining_time":0.1353333264},
{"learn":[3.653957699],"iteration":635,"passed_time":0.2356989305,"remaining_time":0.1348968722},
{"learn":[3.651920725],"iteration":636,"passed_time":0.2359508267,"remaining_time":0.1344586344},
{"learn":[3.65106705],"iteration":637,"passed_time":0.2361881432,"remaining_time":0.1340127082},
{"learn":[3.650612844],"iteration":638,"passed_time":0.2364197111,"remaining_time":0.1335641873},
{"learn":[3.649884732],"iteration":639,"passed_time":0.2366456138,"remaining_time":0.1331131577},
{"learn":[3.646276182],"iteration":640,"passed_time":0.2368806391,"remaining_time":0.1326679399},
{"learn":[3.645808194],"iteration":641,"passed_time":0.2371141649,"remaining_time":0.1322225406},
{"learn":[3.645042989],"iteration":642,"passed_time":0.2373583547,"remaining_time":0.131783721},
{"learn":[3.639864499],"iteration":643,"passed_time":0.2376031277,"remaining_time":0.1313458283},
{"learn":[3.637318478],"iteration":644,"passed_time":0.2378641467,"remaining_time":0.1309174761},
{"learn":[3.636344905],"iteration":645,"passed_time":0.2381135435,"remaining_time":0.1304832731},
{"learn":[3.634754643],"iteration":646,"passed_time":0.2383731462,"remaining_time":0.1300552096},
{"learn":[3.630724975],"iteration":647,"passed_time":0.2385986322,"remaining_time":0.1296091336},
{"learn":[3.629408252],"iteration":648,"passed_time":0.2388445299,"remaining_time":0.1291747766},
{"learn":[3.62790646],"iteration":649,"passed_time":0.2391155465,"remaining_time":0.128754525},
{"learn":[3.627388973],"iteration":650,"passed_time":0.2393515299,"remaining_time":0.1283159508},
{"learn":[3.625163557],"iteration":651,"passed_time":0.2396099662,"remaining_time":0.127889982},
{"learn":[3.623701985],"iteration":652,"passed_time":0.2398439086,"remaining_time":0.1274515104},
{"learn":[3.622342639],"iteration":653,"passed_time":0.2400758097,"remaining_time":0.1270125843},
{"learn":[3.621130639],"iteration":654,"passed_time":0.2403181666,"remaining_time":0.1265797977},
{"learn":[3.619125665],"iteration":655,"passed_time":0.2405532337,"remaining_time":0.1261437689},
{"learn":[3.618878783],"iteration":656,"passed_time":0.2408318733,"remaining_time":0.1257310998},
{"learn":[3.616207429],"iteration":657,"passed_time":0.2410910594,"remaining_time":0.1253087269},
{"learn":[3.61206486],"iteration":658,"passed_time":0.241335874,"remaining_time":0.1248794128},
{"learn":[3.611955873],"iteration":659,"passed_time":0.2415724407,"remaining_time":0.1244464089},
{"learn":[3.610713743],"iteration":660,"passed_time":0.241813423,"remaining_time":0.1240162638},
{"learn":[3.610044025],"iteration":661,"passed_time":0.2420596123,"remaining_time":0.1235893489},
{"learn":[3.607342669],"iteration":662,"passed_time":0.2423166322,"remaining_time":0.1231684843},
{"learn":[3.602510618],"iteration":663,"passed_time":0.2425455341,"remaining_time":0.1227338847},
{"learn":[3.600492392],"iteration":664,"passed_time":0.2428175504,"remaining_time":0.1223216231},
{"learn":[3.597171065],"iteration":665,"passed_time":0.2430526175,"remaining_time":0.1218912526},
{"learn":[3.594358798],"iteration":666,"passed_time":0.2433231341,"remaining_time":0.1214791659},
{"learn":[3.593945251],"iteration":667,"passed_time":0.2435579095,"remaining_time":0.1210497395},
{"learn":[3.593607748],"iteration":668,"passed_time":0.2438085977,"remaining_time":0.1206287681},
{"learn":[3.592238714],"iteration":669,"passed_time":0.2440445812,"remaining_time":0.1202010624},
{"learn":[3.590144654],"iteration":670,"passed_time":0.2442822726,"remaining_time":0.1197747656},
{"learn":[3.587151536],"iteration":671,"passed_time":0.2445100498,"remaining_time":0.119344191},
{"learn":[3.586070865],"iteration":672,"passed_time":0.2447593633,"remaining_time":0.1189246832},
{"learn":[3.585102746],"iteration":673,"passed_time":0.2450018035,"remaining_time":0.118502356},
{"learn":[3.584362847],"iteration":674,"passed_time":0.2452606981,"remaining_time":0.1180884842},
{"learn":[3.581407561],"iteration":675,"passed_time":0.2455031383,"remaining_time":0.1176671846},
{"learn":[3.57919422],"iteration":676,"passed_time":0.2457491193,"remaining_time":0.1172481027},
{"learn":[3.577632204],"iteration":677,"passed_time":0.2460146372,"remaining_time":0.11683881},
{"learn":[3.573911195],"iteration":678,"passed_time":0.2462507873,"remaining_time":0.116416057},
{"learn":[3.573408216],"iteration":679,"passed_time":0.2464838132,"remaining_time":0.1159923827},
{"learn":[3.571076482],"iteration":680,"passed_time":0.2467316687,"remaining_time":0.1155762149},
{"learn":[3.568177107],"iteration":681,"passed_time":0.246987314,"remaining_time":0.1151641728},
{"learn":[3.564824621],"iteration":682,"passed_time":0.247230754,"remaining_time":0.1147469239},
{"learn":[3.562475026],"iteration":683,"passed_time":0.2474754853,"remaining_time":0.1143307798},
{"learn":[3.561226889],"iteration":684,"passed_time":0.2477161343,"remaining_time":0.1139132589},
{"learn":[3.559383467],"iteration":685,"passed_time":0.2479534508,"remaining_time":0.1134947282},
{"learn":[3.555209766],"iteration":686,"passed_time":0.2481928085,"remaining_time":0.1130776551},
{"learn":[3.55345383],"iteration":687,"passed_time":0.2484445797,"remaining_time":0.112666728},
{"learn":[3.552300968],"iteration":688,"passed_time":0.2486838124,"remaining_time":0.1122506033},
{"learn":[3.551253986],"iteration":689,"passed_time":0.2489082987,"remaining_time":0.1118283661},
{"learn":[3.549807725],"iteration":690,"passed_time":0.2491381587,"remaining_time":0.1114091043},
{"learn":[3.547992926],"iteration":691,"passed_time":0.2493640197,"remaining_time":0.1109886099},
{"learn":[3.545438607],"iteration":692,"passed_time":0.2496026276,"remaining_time":0.1105743242},
{"learn":[3.543313763],"iteration":693,"passed_time":0.2498354452,"remaining_time":0.1101579917},
{"learn":[3.542962896],"iteration":694,"passed_time":0.2500645553,"remaining_time":0.1097405603},
{"learn":[3.539800465],"iteration":695,"passed_time":0.2503104947,"remaining_time":0.1093310207},
{"learn":[3.53953187],"iteration":696,"passed_time":0.2505647237,"remaining_time":0.1089255542},
{"learn":[3.536332425],"iteration":697,"passed_time":0.2508230767,"remaining_time":0.1085223054},
{"learn":[3.534993327],"iteration":698,"passed_time":0.2510636007,"remaining_time":0.1081117937},
{"learn":[3.531637011],"iteration":699,"passed_time":0.2513302433,"remaining_time":0.1077129614},
{"learn":[3.531040284],"iteration":700,"passed_time":0.2515658102,"remaining_time":0.1073012514},
{"learn":[3.529973872],"iteration":701,"passed_time":0.251792296,"remaining_time":0.1068861883},
{"learn":[3.527325183],"iteration":702,"passed_time":0.2520347363,"remaining_time":0.1064784021},
{"learn":[3.527200815],"iteration":703,"passed_time":0.2522758018,"remaining_time":0.1060705076},
{"learn":[3.523459911],"iteration":704,"passed_time":0.2525108689,"remaining_time":0.1056605763},
{"learn":[3.522729934],"iteration":705,"passed_time":0.2527403123,"remaining_time":0.1052487986},
{"learn":[3.522260582],"iteration":706,"passed_time":0.2529760042,"remaining_time":0.1048401262},
{"learn":[3.518641591],"iteration":707,"passed_time":0.2532256093,"remaining_time":0.1044376807},
{"learn":[3.516856405],"iteration":708,"passed_time":0.2534683411,"remaining_time":0.1040328452},
{"learn":[3.515083413],"iteration":709,"passed_time":0.2536966598,"remaining_time":0.1036225794},
{"learn":[3.514671214],"iteration":710,"passed_time":0.2539034005,"remaining_time":0.1032040545},
{"learn":[3.512617621],"iteration":711,"passed_time":0.2541245544,"remaining_time":0.1027919546},
{"learn":[3.510747971],"iteration":712,"passed_time":0.2543619958,"remaining_time":0.1023869464},
{"learn":[3.508149266],"iteration":713,"passed_time":0.2546091432,"remaining_time":0.1019862955},
{"learn":[3.504557165],"iteration":714,"passed_time":0.2548306303,"remaining_time":0.1015758456},
{"learn":[3.501367208],"iteration":715,"passed_time":0.2550696963,"remaining_time":0.1011728963},
{"learn":[3.497593362],"iteration":716,"passed_time":0.2553177602,"remaining_time":0.1007739555},
{"learn":[3.496291169],"iteration":717,"passed_time":0.2555707395,"remaining_time":0.1003773656},
{"learn":[3.49330374],"iteration":718,"passed_time":0.2558271762,"remaining_time":0.09998252646},
{"learn":[3.490044385],"iteration":719,"passed_time":0.2560669088,"remaining_time":0.09958157564},
{"learn":[3.488891789],"iteration":720,"passed_time":0.2563008095,"remaining_time":0.09917881531},
{"learn":[3.486869081],"iteration":721,"passed_time":0.2565353766,"remaining_time":0.09877677937},
{"learn":[3.486303638],"iteration":722,"passed_time":0.2567850651,"remaining_time":0.09838100003},
{"learn":[3.486035862],"iteration":723,"passed_time":0.2570345452,"remaining_time":0.09798554487},
{"learn":[3.482668951],"iteration":724,"passed_time":0.2572666547,"remaining_time":0.0975839035},
{"learn":[3.47820549],"iteration":725,"passed_time":0.2574821016,"remaining_time":0.09717644053},
{"learn":[3.474392283],"iteration":726,"passed_time":0.2577407461,"remaining_time":0.09678572722},
{"learn":[3.472268163],"iteration":727,"passed_time":0.2579906012,"remaining_time":0.09639209275},
{"learn":[3.471209164],"iteration":728,"passed_time":0.2582343744,"remaining_time":0.09599659186},
{"learn":[3.470049971],"iteration":729,"passed_time":0.2584711494,"remaining_time":0.09559891826},
{"learn":[3.469078654],"iteration":730,"passed_time":0.2587198381,"remaining_time":0.095206069},
{"learn":[3.468643292],"iteration":731,"passed_time":0.2589522807,"remaining_time":0.09480766563},
{"learn":[3.468134848],"iteration":732,"passed_time":0.2591887641,"remaining_time":0.09441118693},
{"learn":[3.467820182],"iteration":733,"passed_time":0.2594174994,"remaining_time":0.09401233629},
{"learn":[3.465776156],"iteration":734,"passed_time":0.2596855166,"remaining_time":0.09362811144},
{"learn":[3.463037608],"iteration":735,"passed_time":0.2599544503,"remaining_time":0.0932445311},
{"learn":[3.45965637],"iteration":736,"passed_time":0.2601828524,"remaining_time":0.09284679806},
{"learn":[3.457275091],"iteration":737,"passed_time":0.2604145452,"remaining_time":0.09245069221},
{"learn":[3.455522955],"iteration":738,"passed_time":0.2606581102,"remaining_time":0.0920592243},
{"learn":[3.451270508],"iteration":739,"passed_time":0.2608923441,"remaining_time":0.09166487766},
{"learn":[3.450978947],"iteration":740,"passed_time":0.2611045834,"remaining_time":0.09126327545},
{"learn":[3.450608492],"iteration":741,"passed_time":0.2613218215,"remaining_time":0.09086392178},
{"learn":[3.448122004],"iteration":742,"passed_time":0.2615659697,"remaining_time":0.09047436636},
{"learn":[3.445646714],"iteration":743,"passed_time":0.261805244,"remaining_time":0.09008352483},
{"learn":[3.44411263],"iteration":744,"passed_time":0.2620436436,"remaining_time":0.08969279076},
{"learn":[3.443264164],"iteration":745,"passed_time":0.2622645474,"remaining_time":0.08929650811},
{"learn":[3.439521363],"iteration":746,"passed_time":0.2624943658,"remaining_time":0.08890371425},
{"learn":[3.436809225],"iteration":747,"passed_time":0.2627267252,"remaining_time":0.08851221222},
{"learn":[3.435509465],"iteration":748,"passed_time":0.2629711232,"remaining_time":0.08812516947},
{"learn":[3.434450277],"iteration":749,"passed_time":0.2632117306,"remaining_time":0.08773724353},
{"learn":[3.431786753],"iteration":750,"passed_time":0.2634487138,"remaining_time":0.08734850831},
{"learn":[3.430150302],"iteration":751,"passed_time":0.2636863219,"remaining_time":0.08696038276},
{"learn":[3.42696281],"iteration":752,"passed_time":0.263919681,"remaining_time":0.08657126324},
{"learn":[3.426870334],"iteration":753,"passed_time":0.2641698277,"remaining_time":0.08618803397},
{"learn":[3.425200309],"iteration":754,"passed_time":0.2644097685,"remaining_time":0.08580184542},
{"learn":[3.423383783],"iteration":755,"passed_time":0.2646601651,"remaining_time":0.08541941838},
{"learn":[3.422752979],"iteration":756,"passed_time":0.2648784863,"remaining_time":0.08502704383},
{"learn":[3.420845924],"iteration":757,"passed_time":0.2651422546,"remaining_time":0.08464963802},
{"learn":[3.418917862],"iteration":758,"passed_time":0.2653995662,"remaining_time":0.08427048149},
{"learn":[3.417095735],"iteration":759,"passed_time":0.2656310091,"remaining_time":0.08388347656},
{"learn":[3.414391848],"iteration":760,"passed_time":0.2658591612,"remaining_time":0.08349584695},
{"learn":[3.41426711],"iteration":761,"passed_time":0.2660699426,"remaining_time":0.08310321041},
{"learn":[3.411976013],"iteration":762,"passed_time":0.2663047597,"remaining_time":0.08271851644},
{"learn":[3.408614844],"iteration":763,"passed_time":0.2665295376,"remaining_time":0.08233111371},
{"learn":[3.407906721],"iteration":764,"passed_time":0.2667641048,"remaining_time":0.08194714329},
{"learn":[3.407494015],"iteration":765,"passed_time":0.2669783853,"remaining_time":0.08155736573},
{"learn":[3.406287128],"iteration":766,"passed_time":0.2672183261,"remaining_time":0.08117584092},
{"learn":[3.404600442],"iteration":767,"passed_time":0.2674564341,"remaining_time":0.08079413112},
{"learn":[3.404012662],"iteration":768,"passed_time":0.2676947503,"remaining_time":0.08041285737},
{"learn":[3.400398762],"iteration":769,"passed_time":0.2679239855,"remaining_time":0.08002924241},
{"learn":[3.399737714],"iteration":770,"passed_time":0.2681439729,"remaining_time":0.07964328118},
{"learn":[3.399185251],"iteration":771,"passed_time":0.2683934114,"remaining_time":0.07926644792},
{"learn":[3.397245411],"iteration":772,"passed_time":0.2686221883,"remaining_time":0.07888387678},
{"learn":[3.396229831],"iteration":773,"passed_time":0.26891974,"remaining_time":0.07852178453},
{"learn":[3.394002836],"iteration":774,"passed_time":0.2691752603,"remaining_time":0.07814765621},
{"learn":[3.389617243],"iteration":775,"passed_time":0.269410244,"remaining_time":0.07776790549},
{"learn":[3.385426488],"iteration":776,"passed_time":0.2696349803,"remaining_time":0.07738558636},
{"learn":[3.385072258],"iteration":777,"passed_time":0.2698630907,"remaining_time":0.07700463514},
{"learn":[3.383842366],"iteration":778,"passed_time":0.2700989909,"remaining_time":0.07662628624},
{"learn":[3.380110746],"iteration":779,"passed_time":0.2703334331,"remaining_time":0.07624789138},
{"learn":[3.378595218],"iteration":780,"passed_time":0.2705581277,"remaining_time":0.07586713183},
{"learn":[3.377371219],"iteration":781,"passed_time":0.2707817392,"remaining_time":0.0754864695},
{"learn":[3.375814782],"iteration":782,"passed_time":0.2710190557,"remaining_time":0.0751100065},
{"learn":[3.374195887],"iteration":783,"passed_time":0.2712584134,"remaining_time":0.07473446082},
{"learn":[3.373704309],"iteration":784,"passed_time":0.27150177,"remaining_time":0.0743603574},
{"learn":[3.372971757],"iteration":785,"passed_time":0.2717366704,"remaining_time":0.07398428432},
{"learn":[3.371565136],"iteration":786,"passed_time":0.2719754033,"remaining_time":0.07360960723},
{"learn":[3.3700309],"iteration":787,"passed_time":0.2722287575,"remaining_time":0.07323920886},
{"learn":[3.368186663],"iteration":788,"passed_time":0.2725348903,"remaining_time":0.07288322162},
{"learn":[3.366710398],"iteration":789,"passed_time":0.2727512536,"remaining_time":0.0725034978},
{"learn":[3.364598042],"iteration":790,"passed_time":0.2729894033,"remaining_time":0.07212994346},
{"learn":[3.36348442],"iteration":791,"passed_time":0.2732015593,"remaining_time":0.07174990446},
{"learn":[3.362001759],"iteration":792,"passed_time":0.2734536638,"remaining_time":0.07138071678},
{"learn":[3.361580401],"iteration":793,"passed_time":0.2736963956,"remaining_time":0.07100939231},
{"learn":[3.359543675],"iteration":794,"passed_time":0.273935295,"remaining_time":0.07063740312},
{"learn":[3.35766119],"iteration":795,"passed_time":0.2741877328,"remaining_time":0.07026921796},
{"learn":[3.354592969],"iteration":796,"passed_time":0.2744148018,"remaining_time":0.06989486169},
{"learn":[3.350985986],"iteration":797,"passed_time":0.2746535763,"remaining_time":0.06952383761},
{"learn":[3.349589624],"iteration":798,"passed_time":0.2748974745,"remaining_time":0.06915443351},
{"learn":[3.349110856],"iteration":799,"passed_time":0.2751505788,"remaining_time":0.06878764469},
{"learn":[3.345315441],"iteration":800,"passed_time":0.2753749401,"remaining_time":0.06841399885},
{"learn":[3.34397474],"iteration":801,"passed_time":0.275620213,"remaining_time":0.06804588799},
{"learn":[3.343800902],"iteration":802,"passed_time":0.27584874,"remaining_time":0.06767397481},
{"learn":[3.342329465],"iteration":803,"passed_time":0.2761068013,"remaining_time":0.06730961823},
{"learn":[3.34220347],"iteration":804,"passed_time":0.2763521992,"remaining_time":0.06694245818},
{"learn":[3.341279219],"iteration":805,"passed_time":0.2765651467,"remaining_time":0.06656778964},
{"learn":[3.337329521],"iteration":806,"passed_time":0.2767980059,"remaining_time":0.06619828394},
{"learn":[3.336708453],"iteration":807,"passed_time":0.2770325314,"remaining_time":0.06582951242},
{"learn":[3.333252703],"iteration":808,"passed_time":0.2772908011,"remaining_time":0.06546667862},
{"learn":[3.332186769],"iteration":809,"passed_time":0.2775519867,"remaining_time":0.065104787},
{"learn":[3.330594851],"iteration":810,"passed_time":0.2777770979,"remaining_time":0.06473473674},
{"learn":[3.327867442],"iteration":811,"passed_time":0.2779965021,"remaining_time":0.06436372216},
{"learn":[3.327563111],"iteration":812,"passed_time":0.2782231545,"remaining_time":0.06399474772},
{"learn":[3.326308994],"iteration":813,"passed_time":0.2784572635,"remaining_time":0.06362782679},
{"learn":[3.326249879],"iteration":814,"passed_time":0.2786701277,"remaining_time":0.06325640935},
{"learn":[3.322336238],"iteration":815,"passed_time":0.2788867409,"remaining_time":0.0628862259},
{"learn":[3.320491154],"iteration":816,"passed_time":0.2791288063,"remaining_time":0.0625221194},
{"learn":[3.320434271],"iteration":817,"passed_time":0.2793480439,"remaining_time":0.06215323226},
{"learn":[3.319609638],"iteration":818,"passed_time":0.2795825694,"remaining_time":0.06178808921},
{"learn":[3.316182682],"iteration":819,"passed_time":0.2798218854,"remaining_time":0.0614243163},
{"learn":[3.313126612],"iteration":820,"passed_time":0.2800705324,"remaining_time":0.061062881},
{"learn":[3.311222803],"iteration":821,"passed_time":0.2803084737,"remaining_time":0.06069940186},
{"learn":[3.309627335],"iteration":822,"passed_time":0.2805334599,"remaining_time":0.06033344157},
{"learn":[3.307974895],"iteration":823,"passed_time":0.2807540306,"remaining_time":0.05996688031},
{"learn":[3.307321505],"iteration":824,"passed_time":0.2809833907,"remaining_time":0.05960253742},
{"learn":[3.306759087],"iteration":825,"passed_time":0.2812084602,"remaining_time":0.05923761752},
{"learn":[3.30484037],"iteration":826,"passed_time":0.2814450269,"remaining_time":0.05887544093},
{"learn":[3.30201994],"iteration":827,"passed_time":0.281666139,"remaining_time":0.05851035738},
{"learn":[3.299302297],"iteration":828,"passed_time":0.2819045386,"remaining_time":0.05814918709},
{"learn":[3.298132671],"iteration":829,"passed_time":0.2821526857,"remaining_time":0.05779030913},
{"learn":[3.296976183],"iteration":830,"passed_time":0.2823790049,"remaining_time":0.05742725852},
{"learn":[3.293144745],"iteration":831,"passed_time":0.2826184042,"remaining_time":0.05706717778},
{"learn":[3.290284404],"iteration":832,"passed_time":0.282823437,"remaining_time":0.05670049698},
{"learn":[3.288285745],"iteration":833,"passed_time":0.2830733754,"remaining_time":0.05634314187},
{"learn":[3.286662667],"iteration":834,"passed_time":0.2832896554,"remaining_time":0.05597939299},
{"learn":[3.285692682],"iteration":835,"passed_time":0.283525389,"remaining_time":0.05561981314},
{"learn":[3.284565611],"iteration":836,"passed_time":0.2837620806,"remaining_time":0.05526071582},
{"learn":[3.283897383],"iteration":837,"passed_time":0.2839984807,"remaining_time":0.05490185425},
{"learn":[3.280712855],"iteration":838,"passed_time":0.2842495438,"remaining_time":0.05454609838},
{"learn":[3.280468341],"iteration":839,"passed_time":0.2844706559,"remaining_time":0.05418488684},
{"learn":[3.277814895],"iteration":840,"passed_time":0.2847118464,"remaining_time":0.0538278045},
{"learn":[3.276316385],"iteration":841,"passed_time":0.2849533702,"remaining_time":0.05347105997},
{"learn":[3.27557063],"iteration":842,"passed_time":0.2851967269,"remaining_time":0.05311493016},
{"learn":[3.27499628],"iteration":843,"passed_time":0.2854237126,"remaining_time":0.05275604166},
{"learn":[3.273569958],"iteration":844,"passed_time":0.2856535726,"remaining_time":0.05239799261},
{"learn":[3.269665595],"iteration":845,"passed_time":0.285891389,"remaining_time":0.05204169492},
{"learn":[3.267984685],"iteration":846,"passed_time":0.2861402026,"remaining_time":0.05168766352},
{"learn":[3.267702508],"iteration":847,"passed_time":0.2863625645,"remaining_time":0.05132913891},
{"learn":[3.266671924],"iteration":848,"passed_time":0.2865988395,"remaining_time":0.05097340962},
{"learn":[3.265359825],"iteration":849,"passed_time":0.2868447372,"remaining_time":0.05061965951},
{"learn":[3.2618983],"iteration":850,"passed_time":0.2870809707,"remaining_time":0.05026447078},
{"learn":[3.260456253],"iteration":851,"passed_time":0.2873320338,"remaining_time":0.04991213732},
{"learn":[3.258389147],"iteration":852,"passed_time":0.2875701834,"remaining_time":0.04955781589},
{"learn":[3.258108469],"iteration":853,"passed_time":0.2878250372,"remaining_time":0.04920662229},
{"learn":[3.256424936],"iteration":854,"passed_time":0.2880825987,"remaining_time":0.04885611323},
{"learn":[3.254817983],"iteration":855,"passed_time":0.2883565728,"remaining_time":0.04850858235},
{"learn":[3.253898449],"iteration":856,"passed_time":0.2885857247,"remaining_time":0.04815374402},
{"learn":[3.253023652],"iteration":857,"passed_time":0.2888335802,"remaining_time":0.04780229416},
{"learn":[3.252845542],"iteration":858,"passed_time":0.2890903503,"remaining_time":0.04745254876},
{"learn":[3.252316026],"iteration":859,"passed_time":0.289352494,"remaining_time":0.04710389437},
{"learn":[3.24975301],"iteration":860,"passed_time":0.2895780633,"remaining_time":0.04674953636},
{"learn":[3.249151075],"iteration":861,"passed_time":0.2898207119,"remaining_time":0.04639821141},
{"learn":[3.246257135],"iteration":862,"passed_time":0.2900441151,"remaining_time":0.04604408316},
{"learn":[3.243826471],"iteration":863,"passed_time":0.2902636027,"remaining_time":0.04568964116},
{"learn":[3.243190653],"iteration":864,"passed_time":0.2905087922,"remaining_time":0.04533952248},
{"learn":[3.24008797],"iteration":865,"passed_time":0.2907428595,"remaining_time":0.04498792514},
{"learn":[3.240036811],"iteration":866,"passed_time":0.2909593478,"remaining_time":0.04463390226},
{"learn":[3.238676314],"iteration":867,"passed_time":0.2911927069,"remaining_time":0.04428276188},
{"learn":[3.237848782],"iteration":868,"passed_time":0.2914161935,"remaining_time":0.04393040431},
{"learn":[3.236405498],"iteration":869,"passed_time":0.2916575507,"remaining_time":0.04358101332},
{"learn":[3.233378068],"iteration":870,"passed_time":0.2919067392,"remaining_time":0.04323303026},
{"learn":[3.233169169],"iteration":871,"passed_time":0.292125477,"remaining_time":0.04288080396},
{"learn":[3.232434885],"iteration":872,"passed_time":0.292371333,"remaining_time":0.04253282851},
{"learn":[3.229978115],"iteration":873,"passed_time":0.2926137316,"remaining_time":0.0421845883},
{"learn":[3.229648848],"iteration":874,"passed_time":0.2928231799,"remaining_time":0.04183188285},
{"learn":[3.227208761],"iteration":875,"passed_time":0.2930524151,"remaining_time":0.04148230533},
{"learn":[3.226258869],"iteration":876,"passed_time":0.2932832332,"remaining_time":0.04113322427},
{"learn":[3.225331995],"iteration":877,"passed_time":0.293531422,"remaining_time":0.04078682629},
{"learn":[3.221968268],"iteration":878,"passed_time":0.2937797358,"remaining_time":0.04044066897},
{"learn":[3.221166317],"iteration":879,"passed_time":0.2940401716,"remaining_time":0.04009638703},
{"learn":[3.220047503],"iteration":880,"passed_time":0.294283195,"remaining_time":0.03974994348},
{"learn":[3.21982781],"iteration":881,"passed_time":0.2945231775,"remaining_time":0.0394033276},
{"learn":[3.216693405],"iteration":882,"passed_time":0.2947740323,"remaining_time":0.03905839386},
{"learn":[3.214798761],"iteration":883,"passed_time":0.2950216379,"remaining_time":0.0387132466},
{"learn":[3.214395085],"iteration":884,"passed_time":0.2952507064,"remaining_time":0.03836591101},
{"learn":[3.213470696],"iteration":885,"passed_time":0.2954792751,"remaining_time":0.03801877806},
{"learn":[3.211595017],"iteration":886,"passed_time":0.2957088435,"remaining_time":0.03767203981},
{"learn":[3.210965255],"iteration":887,"passed_time":0.2959463683,"remaining_time":0.03732656897},
{"learn":[3.209413583],"iteration":888,"passed_time":0.2961838514,"remaining_time":0.03698133577},
{"learn":[3.208331683],"iteration":889,"passed_time":0.2964072546,"remaining_time":0.0366346045},
{"learn":[3.207110711],"iteration":890,"passed_time":0.2966398639,"remaining_time":0.03628927628},
{"learn":[3.204519413],"iteration":891,"passed_time":0.2968716818,"remaining_time":0.03594410497},
{"learn":[3.201421296],"iteration":892,"passed_time":0.2970988341,"remaining_time":0.0355986285},
{"learn":[3.200691259],"iteration":893,"passed_time":0.2973256532,"remaining_time":0.03525337722},
{"learn":[3.200485067],"iteration":894,"passed_time":0.2975535137,"remaining_time":0.03490851278},
{"learn":[3.197467568],"iteration":895,"passed_time":0.2977760005,"remaining_time":0.03456328577},
{"learn":[3.195838544],"iteration":896,"passed_time":0.2980111092,"remaining_time":0.03421978177},
{"learn":[3.195671746],"iteration":897,"passed_time":0.2982556322,"remaining_time":0.03387758852},
{"learn":[3.194213094],"iteration":898,"passed_time":0.2984904077,"remaining_time":0.03353451744},
{"learn":[3.192884691],"iteration":899,"passed_time":0.2987365553,"remaining_time":0.03319295059},
{"learn":[3.188364239],"iteration":900,"passed_time":0.2989814949,"remaining_time":0.03285146282},
{"learn":[3.185219478],"iteration":901,"passed_time":0.2992236019,"remaining_time":0.03250988136},
{"learn":[3.184120387],"iteration":902,"passed_time":0.2994495046,"remaining_time":0.03216677956},
{"learn":[3.183725321],"iteration":903,"passed_time":0.2996845716,"remaining_time":0.03182491026},
{"learn":[3.181264554],"iteration":904,"passed_time":0.299905892,"remaining_time":0.03148183397},
{"learn":[3.180741589],"iteration":905,"passed_time":0.3001354604,"remaining_time":0.03113988221},
{"learn":[3.179782639],"iteration":906,"passed_time":0.3003717355,"remaining_time":0.03079886594},
{"learn":[3.176377564],"iteration":907,"passed_time":0.3005988462,"remaining_time":0.03045715182},
{"learn":[3.174078182],"iteration":908,"passed_time":0.3008229576,"remaining_time":0.0301153896},
{"learn":[3.171242379],"iteration":909,"passed_time":0.3010759786,"remaining_time":0.02977674513},
{"learn":[3.170421012],"iteration":910,"passed_time":0.3013048388,"remaining_time":0.02943592827},
{"learn":[3.170087224],"iteration":911,"passed_time":0.3015569017,"remaining_time":0.02909759577},
{"learn":[3.167303059],"iteration":912,"passed_time":0.3017853453,"remaining_time":0.02875720158},
{"learn":[3.16705966],"iteration":913,"passed_time":0.3020237032,"remaining_time":0.02841798521},
{"learn":[3.165667683],"iteration":914,"passed_time":0.3022408164,"remaining_time":0.02807701573},
{"learn":[3.164689733],"iteration":915,"passed_time":0.3024673439,"remaining_time":0.02773718},
{"learn":[3.163311455],"iteration":916,"passed_time":0.3026809579,"remaining_time":0.02739642258},
{"learn":[3.159425016],"iteration":917,"passed_time":0.3029112761,"remaining_time":0.02705743425},
{"learn":[3.159327058],"iteration":918,"passed_time":0.303128056,"remaining_time":0.02671748915},
{"learn":[3.15819426],"iteration":919,"passed_time":0.3033607902,"remaining_time":0.02637919915},
{"learn":[3.157086603],"iteration":920,"passed_time":0.303591525,"remaining_time":0.02604096686},
{"learn":[3.153354154],"iteration":921,"passed_time":0.3038409219,"remaining_time":0.02570454654},
{"learn":[3.153261317],"iteration":922,"passed_time":0.3040894023,"remaining_time":0.02536823833},
{"learn":[3.153168454],"iteration":923,"passed_time":0.3043068487,"remaining_time":0.02502956764},
{"learn":[3.152080399],"iteration":924,"passed_time":0.3045372085,"remaining_time":0.0246922061},
{"learn":[3.151635144],"iteration":925,"passed_time":0.3047776909,"remaining_time":0.02435588459},
{"learn":[3.147762655],"iteration":926,"passed_time":0.3050266712,"remaining_time":0.02402043905},
{"learn":[3.147172317],"iteration":927,"passed_time":0.3052703611,"remaining_time":0.0236847694},
{"learn":[3.146254125],"iteration":928,"passed_time":0.3055183,"remaining_time":0.0233496225},
{"learn":[3.144869828],"iteration":929,"passed_time":0.3057688632,"remaining_time":0.02301486067},
{"learn":[3.143466218],"iteration":930,"passed_time":0.3060125948,"remaining_time":0.0226797734},
{"learn":[3.141919643],"iteration":931,"passed_time":0.3062646993,"remaining_time":0.02234549308},
{"learn":[3.141054135],"iteration":932,"passed_time":0.306513263,"remaining_time":0.02201113464},
{"learn":[3.139390417],"iteration":933,"passed_time":0.3067642011,"remaining_time":0.0216771277},
{"learn":[3.139025283],"iteration":934,"passed_time":0.3070006845,"remaining_time":0.02134229357},
{"learn":[3.137824183],"iteration":935,"passed_time":0.3072465822,"remaining_time":0.02100831331},
{"learn":[3.135620453],"iteration":936,"passed_time":0.3074938129,"remaining_time":0.02067461069},
{"learn":[3.13443178],"iteration":937,"passed_time":0.3077596224,"remaining_time":0.02034232046},
{"learn":[3.132765713],"iteration":938,"passed_time":0.3080074779,"remaining_time":0.02000900549},
{"learn":[3.131434124],"iteration":939,"passed_time":0.3082404622,"remaining_time":0.01967492312},
{"learn":[3.128384262],"iteration":940,"passed_time":0.3085003564,"remaining_time":0.01934274286},
{"learn":[3.128120455],"iteration":941,"passed_time":0.3087415886,"remaining_time":0.01900956703},
{"learn":[3.126314615],"iteration":942,"passed_time":0.3090124802,"remaining_time":0.01867837897},
{"learn":[3.125409666],"iteration":943,"passed_time":0.3092444646,"remaining_time":0.01834501061},
{"learn":[3.123072589],"iteration":944,"passed_time":0.3094835307,"remaining_time":0.01801226898},
{"learn":[3.122921099],"iteration":945,"passed_time":0.3097375097,"remaining_time":0.01768057667},
{"learn":[3.122182662],"iteration":946,"passed_time":0.309986365,"remaining_time":0.01734876172},
{"learn":[3.120040951],"iteration":947,"passed_time":0.3102291802,"remaining_time":0.01701679047},
{"learn":[3.118767799],"iteration":948,"passed_time":0.3104808265,"remaining_time":0.01668548172},
{"learn":[3.118203218],"iteration":949,"passed_time":0.3107265159,"remaining_time":0.01635402715},
{"learn":[3.116343362],"iteration":950,"passed_time":0.31098691,"remaining_time":0.01602351061},
{"learn":[3.11480829],"iteration":951,"passed_time":0.3112011905,"remaining_time":0.01569081633},
{"learn":[3.112607903],"iteration":952,"passed_time":0.3114467966,"remaining_time":0.01535991547},
{"learn":[3.111661241],"iteration":953,"passed_time":0.3116937358,"remaining_time":0.0150292577},
{"learn":[3.110249676],"iteration":954,"passed_time":0.311942966,"remaining_time":0.01469888321},
{"learn":[3.107333579],"iteration":955,"passed_time":0.3121891136,"remaining_time":0.01436853661},
{"learn":[3.107149851],"iteration":956,"passed_time":0.3124205982,"remaining_time":0.01403770713},
{"learn":[3.106867336],"iteration":957,"passed_time":0.312652666,"remaining_time":0.01370711062},
{"learn":[3.10364681],"iteration":958,"passed_time":0.3128938149,"remaining_time":0.01337710783},
{"learn":[3.102703811],"iteration":959,"passed_time":0.3131364634,"remaining_time":0.01304735264},
{"learn":[3.101469264],"iteration":960,"passed_time":0.3133928585,"remaining_time":0.01271833661},
{"learn":[3.09863569],"iteration":961,"passed_time":0.3136207607,"remaining_time":0.01238834606},
{"learn":[3.09645939],"iteration":962,"passed_time":0.3138717404,"remaining_time":0.0120594542},
{"learn":[3.096240186],"iteration":963,"passed_time":0.3141200542,"remaining_time":0.01173062443},
{"learn":[3.094838828],"iteration":964,"passed_time":0.3143632859,"remaining_time":0.01140177721},
{"learn":[3.094176802],"iteration":965,"passed_time":0.3146028102,"remaining_time":0.01107297676},
{"learn":[3.093182279],"iteration":966,"passed_time":0.3148287128,"remaining_time":0.01074389609},
{"learn":[3.090150687],"iteration":967,"passed_time":0.3150657377,"remaining_time":0.01041539629},
{"learn":[3.088612829],"iteration":968,"passed_time":0.3152858501,"remaining_time":0.01008654423},
{"learn":[3.087153684],"iteration":969,"passed_time":0.3155107947,"remaining_time":0.009758065815},
{"learn":[3.085866843],"iteration":970,"passed_time":0.3157763959,"remaining_time":0.009431014912},
{"learn":[3.082669094],"iteration":971,"passed_time":0.31600963,"remaining_time":0.009103158066},
{"learn":[3.081047548],"iteration":972,"passed_time":0.3162583187,"remaining_time":0.008775924568},
{"learn":[3.079684322],"iteration":973,"passed_time":0.3164964683,"remaining_time":0.008448571023},
{"learn":[3.07613431],"iteration":974,"passed_time":0.3167122901,"remaining_time":0.008120827952},
{"learn":[3.074005935],"iteration":975,"passed_time":0.316962895,"remaining_time":0.007794169549},
{"learn":[3.072988853],"iteration":976,"passed_time":0.3171974205,"remaining_time":0.007467288303},
{"learn":[3.072344268],"iteration":977,"passed_time":0.3174699367,"remaining_time":0.007141450518},
{"learn":[3.070654438],"iteration":978,"passed_time":0.3177449105,"remaining_time":0.006815774383},
{"learn":[3.069724506],"iteration":979,"passed_time":0.3181169855,"remaining_time":0.006492183377},
{"learn":[3.067763166],"iteration":980,"passed_time":0.3183557599,"remaining_time":0.006165911762},
{"learn":[3.066737893],"iteration":981,"passed_time":0.3186276512,"remaining_time":0.005840425379},
{"learn":[3.065248174],"iteration":982,"passed_time":0.3188524291,"remaining_time":0.005514233261},
{"learn":[3.063186837],"iteration":983,"passed_time":0.3191260283,"remaining_time":0.005189041111},
{"learn":[3.062880371],"iteration":984,"passed_time":0.3193758001,"remaining_time":0.004863590864},
{"learn":[3.061288645],"iteration":985,"passed_time":0.3195906638,"remaining_time":0.004537798472},
{"learn":[3.059970575],"iteration":986,"passed_time":0.3198218568,"remaining_time":0.004212445935},
{"learn":[3.059576341],"iteration":987,"passed_time":0.3200647136,"remaining_time":0.003887425671},
{"learn":[3.058175919],"iteration":988,"passed_time":0.3202851176,"remaining_time":0.003562321833},
{"learn":[3.056830702],"iteration":989,"passed_time":0.3205053133,"remaining_time":0.003237427407},
{"learn":[3.056336579],"iteration":990,"passed_time":0.3207249675,"remaining_time":0.002912739361},
{"learn":[3.055810414],"iteration":991,"passed_time":0.3209504119,"remaining_time":0.002588309773},
{"learn":[3.055476518],"iteration":992,"passed_time":0.3211708992,"remaining_time":0.002264044607},
{"learn":[3.053331734],"iteration":993,"passed_time":0.3213809724,"remaining_time":0.001939925387},
{"learn":[3.050890374],"iteration":994,"passed_time":0.3216004183,"remaining_time":0.001616082504},
{"learn":[3.04972623],"iteration":995,"passed_time":0.321809825,"remaining_time":0.001292408936},
{"learn":[3.047217327],"iteration":996,"passed_time":0.3220305206,"remaining_time":0.0009689985574},
{"learn":[3.047155483],"iteration":997,"passed_time":0.3222514245,"remaining_time":0.0006457944378},
{"learn":[3.04430671],"iteration":998,"passed_time":0.3224828257,"remaining_time":0.0003228056314},
{"learn":[3.042664195],"iteration":999,"passed_time":0.3227533007,"remaining_time":0}
]}